{
    "id": "2603.27725v1",
    "title": "TerraSkipper: A Centimeter-Scale Robot for Multi-Terrain Skipping and Crawling",
    "authors": [
        "Shashwat Singh",
        "Sheri Zhang",
        "Spencer Matonis",
        "Zeynep Temel"
    ],
    "abstract": "弹涂鱼是一种独特的双栖鱼类，能在陆地、水域乃至高黏性基质（如泥滩）等多种环境中运动。这种多环境运动能力主要得益于其强健的尾部结构——通过储存并快速释放能量实现爆发式跳跃。受此生物机制启发，我们设计并开发了一款多地形厘米级跳跃爬行机器人。该机器人主体采用3D打印技术，集成了板载传感、计算与动力系统，配备两片带霍尔效应传感器的侧鳍实现步态控制爬行，同时通过10毫米行星齿轮电机驱动的旋转弹簧尾结构，可在多种基质上实现连续爆发式跳跃，从而完成多地形运动。通过对尾部结构进行建模与实验测试，我们确定了25毫米的最优尾长，此时能产生最大平均推进力（4牛，峰值达6牛）以实现前进运动。此外，我们在鳍状爬行失效的基质上评估了跳跃性能，并通过调节均匀沙土与膨润土粉末的含水量对比了跳跃与爬行模式。实验表明跳跃模式始终能产生更高的平均速度，尤其在黏性介质与颗粒介质中表现突出。最后，在草地、流沙与硬质地表的户外测试证实：在缠结地形与颗粒地形采用跳跃模式，在坚实地面采用爬行模式，能有效扩展机器人在真实环境中的作业范围。",
    "url": "https://arxiv.org/abs/2603.27725v1",
    "html_url": "https://arxiv.org/html/2603.27725v1",
    "html_content": "TerraSkipper: A Centimeter-Scale Robot for Multi-Terrain Skipping and Crawling\nShashwat Singh\n1\n, Sheri Zhang\n1,2\n, Spencer Matonis\n3\n, and Zeynep Temel\n1\nThis work is supported in part by National Science Foundation grants 2308654.\n1\nThe Robotics Institute, Carnegie Mellon University, Pittsburgh, PA 15213, USA.\n2\nDepartment of Mechanical Engineering, Carnegie Mellon University, Pittsburgh, PA 15213, USA.\n3\nEdulis Therapeutics, Nashville, TN 37204.Corresponding author: shashwa3@andrew.cmu.edu.\nAbstract\nMudskippers are unique amphibious fish capable of locomotion in diverse environments, including terrestrial surfaces, aquatic habitats, and highly viscous substrates such as mud. This versatile locomotion is largely enabled by their powerful tail, which stores and rapidly releases energy to produce impulsive jumps. Inspired by this biological mechanism, we present the design and development of a multi-terrain centimeter-scale skipping and crawling robot. The robot is predominantly 3D printed and features onboard sensing, computation, and power. It is equipped with two side fins for crawling, each integrated with a hall effect sensor for gait control, while a rotary springtail driven by a\n10\nmm\n10\\text{\\,}\\mathrm{mm}\nplanetary gear motor enables continuous impulsive skipping across a range of substrates to achieve multi-terrain locomotion. We modeled and experimentally characterized the tail, identifying an optimal length of\n25\nmm\n25\\text{\\,}\\mathrm{mm}\nthat maximizes the mean propulsive force (\n4\nN\n4\\text{\\,}\\mathrm{N}\n, peaks up to\n6\nN\n6\\text{\\,}\\mathrm{N}\n) for forward motion. In addition, we evaluated skipping on substrates where fin based crawling alone fails, and varied the moisture content of uniform sand and bentonite clay powder to compare skipping with crawling. Skipping consistently produced higher mean velocities than crawling, particularly on viscous and granular media. Finally, outdoor tests on grass, loose sand, and hard ground confirmed that combining skipping on entangling and granular terrain with crawling on firm ground extends the operational range of the robot in real-world environments.\nI\nIntroduction\nRobots traversing natural environments face significant challenges when encountered with soft, heterogeneous, and deformable terrains such as mud, sand, clay, and grass\n[\n15\n,\n19\n]\n. Unlike rigid or artificial surfaces, these substrates vary widely in water content, compaction, and particle size, producing unpredictable mechanical responses under load. Locomotion mechanisms that are effective on flat or firm ground often fail in these conditions, particularly on the centimeter-scale\n[\n9\n,\n26\n,\n25\n,\n11\n,\n2\n,\n7\n]\nwhere robots cannot rely on heavy actuation\n[\n23\n]\nor large appendages\n[\n1\n]\n. Overcoming this challenge is essential for the deployment of small robots in real-world applications such as environmental monitoring\n[\n8\n]\n, wetland exploration\n[\n1\n]\n, and search and rescue operations in disaster zones\n[\n20\n,\n29\n,\n4\n]\n.\nFigure 1:\nTerraSkipper with representative challenging terrains shown in the surrounding circular pictures, on which the robot can locomote. A U.S. quarter and a ruler indicate scale.\nBiological systems provide valuable inspiration for designing robots capable of locomotion in complex environments\n[\n3\n,\n1\n,\n29\n]\n. Robots like mudskipper robot\n[\n17\n]\n, salamander robot\n[\n6\n]\n, and small fish robots\n[\n5\n]\nexploit impulsive tail strikes and fin movements to propel themselves across semi-aquatic terrains where conventional crawling or swimming alone would be ineffective\n[\n14\n,\n21\n]\n. Previous robotic studies have demonstrated the utility of tails for self-righting and inertial reorientation\n[\n13\n,\n16\n]\n, jumping\n[\n24\n,\n22\n]\n, or propulsion on solid ground\n[\n30\n]\nand in fluids\n[\n17\n,\n5\n]\n. Similarly, robots equipped with legs or paddles have been used to navigate granular substrates and shallow water\n[\n1\n,\n15\n]\n. However, these approaches often focus on isolated functions such as jumping on rigid surfaces\n[\n12\n]\nor paddling in fluids\n[\n27\n]\nand rarely address the combined challenge of mobility in environments with variable rheology and deformability.\nGranular and muddy substrates, in particular, have been studied extensively in the context of terradynamics, where resistive force theory and empirical models have revealed how particle size, packing fraction, and intrusion depth influence locomotion\n[\n15\n,\n10\n,\n31\n]\n. Yet these studies have largely considered either simple intruders or larger robots, leaving open questions about how centimeter-scale robots interact with real, messy substrates under varying water content. At small scales, substrate robot interactions are further complicated by surface tension effects, local compaction, and stick–slip dynamics\n[\n15\n]\n, making it difficult to generalize from existing models. Consequently, there remains a lack of systematic studies that connect substrate properties to robotic performance in biologically inspired, tail driven locomotion.\nIn this work, we introduce\nTerraSkipper\n(Fig.\n1\n), a centimeter-scale robot that integrates a rotary spring actuated tail with lightweight fin to achieve multi-modal locomotion. The robot is predominantly 3D-printed, fully untethered, and features onboard sensing, computation, and power with an average runtime of\n30\nmin\n30\\text{\\,}\\mathrm{min}\ndetailed in section\nII-A\n. Leveraging micromagnets and hall effect sensors, the fins provide lightweight (\n280\nmg\n280\\text{\\,}\\mathrm{mg}\n) feedback for gait control, enabling effective closed-loop synchronization while reducing overall mass and power requirements. This weight reduction enables continuous impulsive tail actuation with a single low-voltage motor, optimized through the springtail’s impact force characterization discussed in section\nII-B\n. Pectoral fin gait patterns were designed and evaluated using overhead video tracking, with and without encoder feedback, to assess their ability to move in a straight line in section\nII-C\n. The resulting robot consumes less than\n1\nW\n1\\text{\\,}\\mathrm{W}\nof power, and can be fabricated for under $\n50\n50\n, providing an accessible platform for investigating amphibious locomotion at small scales.\nWe further present a comprehensive experimental characterization of TerraSkipper across diverse substrates in section\nIII-B\nalong with uniform black aquarium sand and bentonite clay powder with controlled water content in section\nIII-C\n. By systematically varying water content and compaction, we capture transitions between dry, and wide range of moisture content conditions, and quantify locomotor performance in terms of mean velocity and standard deviations across three trials. These experiments constitute a systematic study of impulsive tail-substrate interactions for a centimeter-scale robot, and highlight scenarios where tail driven propulsion succeeds and fin based locomotion alone fails. Among the representative centimeter-scale robots compared in Table\nI\n, TerraSkipper is the only one demonstrated locomotion on both rigid and deformable terrain. Beyond reporting performance metrics, this work contributes a reproducible methodological framework for testing robots on deformable terrains, bridging bio-inspired design and granular physics. Collectively, these results advance the design of substrate aware robots, and suggest pathways for small amphibious platforms capable of robust locomotion in challenging environments, and other unstructured natural terrains.\nTABLE I:\nComparison with representative centimeter-scale robots.\nTerra\nBuffalo\nMM3P\n[\n7\n]\nDASH\n[\n2\n]\nVeloci\nRobot\nSkipper\nByte\n[\n25\n]\nRoACH\n[\n11\n]\nSize (cm)\n5.8×2.7×3.2\n2.9×3.0×2.1\n4.7×4.7×3.0\n10×4.5×3.0\n10×6.5×4.2\nMass (g)\n28\n11.4\n14.5\n16.2\n29.1\nSpeed (mm/s)\n31\n235.7\n57\n1500\n2700\nSpeed (BL/s)\n0.54\n8.1\n1.2\n15\n27\nTerrain\nRigid /\nRigid\nRigid\nRigid\nRigid\nDeformable\nFigure 2:\nExploded view of the CAD model of TerraSkipper, highlighting key components: tail motor with propeller, spring steel element, hall effect sensor placement with embedded fin magnets, fin motors, chassis, battery, custom PCB, and PCB holder.\nII\nDesign and Characterization\nTerraSkipper is a centimeter-scale robot designed for autonomous operation in challenging terrains. It employs an impulsive spring actuated tail for skipping and soft fins with embedded magnets and hall effect sensors for coordinated gait control.\nII-A\nRobot Design\nTerraSkipper was developed to satisfy three major requirements: (1) a palm-sized form factor, (2) locomotion across heterogeneous terrains, and (3) untethered operation with onboard power and control. To meet these goals, we designed a compact and lightweight platform (Fig.\n2\n) measuring\n5.8\ncm\n5.8\\text{\\,}\\mathrm{cm}\nin length,\n2.7\ncm\n2.7\\text{\\,}\\mathrm{cm}\nin width (\n6.6\ncm\n6.6\\text{\\,}\\mathrm{cm}\nwith fins), and\n3.2\ncm\n3.2\\text{\\,}\\mathrm{cm}\nin height, within a total mass of\n28\ng\n28\\text{\\,}\\mathrm{g}\n. The design integrates two complementary modes of locomotion: springtail loaded skipping and fin driven crawling motion within a lightweight chassis to enable effective mobility on diverse substrates.\nThe chassis is fabricated using 3D-printed PLA (Bambu Lab X1-Carbon) and houses the custom PCB with electronics and sensor, actuators and battery. The fins are printed from TPU and embed two Neodymium magnets (SuperMagnetMan, D1018A,\n3.18\nmm\n3.18\\text{\\,}\\mathrm{mm}\ndiameter,\n1.59\nmm\n1.59\\text{\\,}\\mathrm{mm}\nthickness) using super glue (Loctite 401), which interact with side mounted hall effect sensors (DRV5032, Texas Instruments) to provide feedback for gait control. The custom PCB hosts Xiao ESP32-S3 (Seeed Studio) dev board, which provides onboard computation and Wi-Fi-based communication for teleoperation. Two dual H-bridge motor drivers (DRV8833, Texas Instruments) supply power: one drives both fin actuators (Pololu,\n6\nV\n6\\text{\\,}\\mathrm{V}\n, 700:1 Sub-Micro Plastic Planetary Gearmotors), while the other is dedicated to the tail actuator (E-S motor, RobotShop, 171:1,\n10\nmm\n10\\text{\\,}\\mathrm{mm}\nPlanetary Gear Motor) to ensure sufficient current delivery by using both the driver output. Power is provided by a\n3.7\nV\n3.7\\text{\\,}\\mathrm{V}\n,\n100\nmA\nh\n100\\text{\\,}\\mathrm{mA}\\text{\\,}\\mathrm{h}\nlithium-polymer battery, positioned at the rear of the chassis to maintain an optimal center of gravity during tail driven jumps. To improve landing stability, the underside of the chassis is curved upward at\n45\n°\n45\\text{\\,}\\mathrm{\\SIUnitSymbolDegree}\nin front of the fins, reducing the likelihood of overturning when the tail generates large impulses.\nThe tail mechanism consists of a\n3\nV\n3\\text{\\,}\\mathrm{V}\nDC motor (60 rpm) housed inside a propeller assembly. The motor is rigidly mounted to the chassis, while the propeller rotates freely around it, ensuring compact packaging without increasing the robot’s width. This encapsulated design balances weight distribution between the two sides of the robot while eliminating additional gearboxes or linkages, thereby simplifying the mechanism. A\n0.1\nmm\n0.1\\text{\\,}\\mathrm{mm}\nthick,\n10\nmm\n10\\text{\\,}\\mathrm{mm}\nwide spring steel element (Blue tempered, 1095 Shim sheet) is bonded using super glue (Loctite 401) into a slot within the propeller such that it remains perpendicular to the tangential face, ensuring full energy release during each skipping motion. The length of the spring steel sheet was optimized through characterization explained in the next section\nII-B\nto generate maximum impact force for forward propulsion.\nFigure 3:\nThe four transition phases of the spring steel during the flicking motion of the jumper mechanism. Free Rotation: the spring rotates with the motor shaft without contacting the curved wall; Load: the spring tip engages the hollow cylinder and begins to bend, storing elastic energy; Latch: the spring is fully conformed and constrained inside the\n270\n°\n270\\text{\\,}\\mathrm{\\SIUnitSymbolDegree}\narc, storing maximum energy; Unlatch: the spring tip exits the arc boundary, releasing stored energy as a rapid snapping motion that propels the robot forward.\nII-B\nTail Characterization and Modeling\nThe springtail mechanism of TerraSkipper is motivated by latch mediated spring systems\n[\n18\n]\nin biological and engineered jumpers, where elastic energy is gradually stored in a compliant element and then released in a rapid impulsive motion. In our design, the tail consists of a rectangular spring steel sheet (\n25\nmm\n25\\text{\\,}\\mathrm{mm}\nlong,\n10\nmm\n10\\text{\\,}\\mathrm{mm}\nwide, and\n0.1\nmm\n0.1\\text{\\,}\\mathrm{mm}\nthick) mounted to a micro-planetary gear motor (E-S motor, RobotShop, 171:1,\n10\nmm\n10\\text{\\,}\\mathrm{mm}\nPlanetary Gear Motor) that drives a rotating propeller hub. As the hub rotates, the springtail moves through four distinct phases of motion (Fig.\n3\n). In the\nfree rotation\nphase, the spring rotates without contacting the chassis. During the\nload\nphase, the tail tip engages with the curved housing, bending gradually and storing elastic strain energy. The\nlatch\nphase occurs when the spring conforms fully to the\n270\n°\n270\\text{\\,}\\mathrm{\\SIUnitSymbolDegree}\narc of the housing, reaching maximum stored energy. Finally, in the\nunlatch\nphase, the tail exits the arc boundary and snaps back to equilibrium, releasing the stored energy as an impulsive force that propels the robot forward.\nFigure 4:\nA) Experimental setup for tail characterization. The robot was mounted to the end effector of a UR5e robot arm via a 3D-printed mount. A force/torque sensor fixed on the table with an additional flat mount is used to record the tail’s impact force and frequency. B) Force measured by the force/torque sensor for different tail lengths. For each length, points show all peaks from\n10\ns\n10\\text{\\,}\\mathrm{s}\nrecording; the square marker indicates the mean with a\n95\n%\n95\\text{\\,}\\mathrm{\\char 37\\relax}\nbootstrap confidence interval. The annotation\nn\nn\nreports the number of peaks (tail strikes) detected within the\n10\ns\n10\\text{\\,}\\mathrm{s}\nwindow.\nII-B\n1\nTail characterization\nTo quantify the force output of the springtail mechanism, we conducted a series of tail characterization experiments for different tail lengths. The characterization setup and results are shown in the Fig.\n4\n. The robot was rigidly mounted to the end effector of a UR5e robot arm using a 3D-printed fixture, with the tail aligned against a flat surface mounted on top of a six-axis force/torque sensor (NRS-60500-D50). This setup in Fig.\n4\n-A allowed repeatable motor actuation sequences while measuring both the magnitude and frequency of tail strikes. Characterization data were used to optimize springtail dimensions and motor actuation speed, ensuring reliable unlatching and maximizing the impulsive forces generated during skipping locomotion.\nFor each configuration, all detected peaks from a\n10\ns\n10\\text{\\,}\\mathrm{s}\nrecording are plotted in Fig.\n4\n-B as individual points, while square markers indicate the mean force with a\n95\n%\n95\\text{\\,}\\mathrm{\\char 37\\relax}\nbootstrap confidence interval. The number of tail strikes\nn\nn\nwithin the recording window is also annotated. Across lengths, we observed a clear trade-off: longer tails produced more frequent strikes but at reduced peak forces, whereas shorter tails generated higher peak forces. Based on this trend, we selected a spring steel length of\n25\nmm\n25\\text{\\,}\\mathrm{mm}\nas the optimized configuration, as it consistently delivered mean force around\n4\nN\n4\\text{\\,}\\mathrm{N}\n(with peaks up to\n6\nN\n6\\text{\\,}\\mathrm{N}\n) while maintaining reliable and repeatable operation across trials. This balance of force output and consistency makes the\n25\nmm\n25\\text{\\,}\\mathrm{mm}\ntail the most effective choice to enable robust skipping locomotion.\nThe observed trade-off is further explained by geometric and actuation constraints: longer tails tend to roll within the hollow cylinder without striking the force/torque sensor, reducing measured peak forces, whereas shorter tails require higher motor torque to bend inside the housing and frequently jam, resulting in a low strike count (\nn\n=\n3\nn=3\n).\nII-B\n2\nTail force model\nThe springtail at unlatch can be approximated as a short cantilever of effective length\nL\neff\nL_{\\text{eff}}\nthat conforms to the housing arc of radius\nR\nR\n. For a rectangular strip of width\nb\nb\nand thickness\nt\nt\nwith Young’s modulus\nE\nE\n, the area moment is\nI\n=\nb\n​\nt\n3\n12\n.\nI=\\frac{b\\,t^{3}}{12}.\nThe equivalent tip stiffness of a cantilever of length\nL\neff\nL_{\\text{eff}}\nis\nk\n=\n3\n​\nE\n​\nI\nL\neff\n3\n.\nk=\\frac{3EI}{L_{\\text{eff}}^{3}}.\nWhen latched against the arc, the deflection is approximated by\nδ\n≈\nL\neff\n2\n2\n​\nR\n.\n\\delta\\approx\\frac{L_{\\text{eff}}^{2}}{2R}.\nCombining\nF\n≈\nk\n​\nδ\nF\\approx k\\delta\nyields a compact expression for the peak elastic force at unlatch:\nF\n≈\n3\n​\nE\n​\nI\n2\n​\nR\n​\nL\neff\n,\nwith\n​\nL\neff\n=\nR\n​\nθ\n,\n\\boxed{F\\approx\\frac{3EI}{2RL_{\\text{eff}}}},\\quad\\text{with }L_{\\text{eff}}=R\\theta,\nwhere\nθ\n\\theta\nis the engaged arc angle (in radians).\nIntuition\nThe model highlights that peak force grows rapidly as the engaged arc shortens:\nF\n∝\n1\n/\nL\neff\nF\\propto 1/L_{\\text{eff}}\n(or\nF\n∝\n1\n/\nθ\nF\\propto 1/\\theta\nat fixed\nR\nR\n). Tail thickness also strongly influences force since\nI\n∝\nt\n3\nI\\propto t^{3}\n.\nNumerical estimate for TerraSkipper\nUsing\nE\n≈\n200\nGPa\nE\\approx$200\\text{\\,}\\mathrm{GPa}$\n(1095 spring steel),\nb\n=\n10\nmm\nb=$10\\text{\\,}\\mathrm{mm}$\n,\nt\n=\n0.10\nmm\nt=$0.10\\text{\\,}\\mathrm{mm}$\n, and\nR\n=\n11\nmm\nR=$11\\text{\\,}\\mathrm{mm}$\n,\nI\n=\n8.33\n×\n10\n−\n16\n​\nm\n4\n,\n3\n​\nE\n​\nI\n2\n​\nR\n≈\n2.27\n×\n10\n−\n2\n​\nN\nm\n.\nI=8.33\\times 10^{-16}\\ $\\mathrm{m}^{4}$,\\qquad\\frac{3EI}{2R}\\approx 2.27\\times 10^{-2}\\ $\\mathrm{N}\\text{\\,}\\mathrm{m}$.\nThe force can therefore be expressed as\nF\n​\n[\nN\n]\n≈\n2.27\n×\n10\n−\n2\nL\neff\n​\n[\nm\n]\nor\nF\n​\n[\nN\n]\n≈\n2.06\nθ\n​\n[\nrad\n]\n.\nF~[$\\mathrm{N}$]\\approx\\frac{2.27\\times 10^{-2}}{L_{\\text{eff}}~[$\\mathrm{m}$]}\\quad\\text{or}\\quad F~[$\\mathrm{N}$]\\approx\\frac{2.06}{\\theta~[\\text{rad}]}.\nEngaged angle\nθ\n\\theta\nL\neff\nL_{\\text{eff}}\n(mm)\nPredicted\nF\nF\n(N)\n45\n∘\n45^{\\circ}\n(\nπ\n/\n4\n\\pi/4\nrad)\n8.64\n2.6\n30\n∘\n30^{\\circ}\n(\nπ\n/\n6\n\\pi/6\nrad)\n5.76\n3.9\n20\n∘\n20^{\\circ}\n(\n0.35\n0.35\nrad)\n3.84\n5.9\nTABLE II:\nPredicted peak force values from the compact tail force model for different engaged arc angles.\nIn practice, the engaged angle\nθ\n\\theta\nis not constant but varies considerably across strikes due to small differences in unlatching conditions, motor speed, and spring seating. Model predictions in Table\nII\n(for\nθ\n∈\n[\n20\n∘\n,\n45\n∘\n]\n\\theta\\!\\in\\![20^{\\circ},45^{\\circ}]\n) align with the measured\n2\nN\nto\n6\nN\n2\\text{\\,}\\mathrm{N}6\\text{\\,}\\mathrm{N}\nrange, supporting the interpretation that variability in engaged angle at unlatch is the primary source of force spread. Thus, while the compact model captures the scaling trend, the inherent inconsistency in\nθ\n\\theta\ncontributes to the variation in experimental outcomes.\nII-C\nGait Control and Evaluation\nMaintaining straight trajectories is a significant challenge for centimeter-scale robots, as small asymmetries in friction or actuation rapidly accumulate into drift\n[\n28\n]\n. To mitigate this, we implemented a lightweight encoder by using a pair of hall effect sensor and a magnet embedded in the fin, to achieve controllable locomotion. Two gait patterns were implemented and evaluated: a\nsynchronous gait\n, in which both fins moved together and each cycle was validated by simultaneous sensor detection, and an\nasynchronous gait\n, in which the fins moved alternately, with each waiting for the other to complete a rotation before proceeding.\nFigure 5:\nTop-down trajectories of TerraSkipper tracked from overhead video on a smooth surface. For each condition, Encoder (Sync gait), Encoder (Async gait), and No encoder, three trials were performed and plotted to illustrate deviation from a straight path on a smooth acrylic surface.\nFor evaluation, robot trajectories were tracked from overhead video using tracking software (Tracker, physlets.org/tracker/) and plotted in the X–Y plane (Fig.\n5\n). With encoder feedback, the robot maintained nearly straight trajectories in both gait conditions, deviating by under\n1\ncm\n1\\text{\\,}\\mathrm{cm}\nfrom the centerline over three trials. In contrast, when encoder feedback was disabled, the robot exhibited substantially larger drift, with deviations of up to\n6\ncm\n6\\text{\\,}\\mathrm{cm}\nin both positive and negative\ny\ny\ndirections. These results highlight the importance of closed-loop control by using encoder feedback for maintaining directional stability and consistent locomotion, regardless of gait choice.\nFigure 6:\nExperimental setup for tracking robot locomotion across various terrains. A clear container with different test beds was placed inside a light box, with rulers for scale calibration. A top-down video was recorded using a fixed overhead camera.\nIII\nExperimental Setup and Mobility Results\nWe evaluated TerraSkipper across a range of natural and artificial substrates to assess its locomotion performance under varying compliance, friction, and heterogeneity in Fig.\n7\n. Substrates included bentonite clay mud, non-uniform desert beach sand, uniform black aquarium sand, artificial and natural grass, and flat rigid acrylic surfaces. It is essential to have such evaluations for understanding robot performance and enabling deployment of centimeter-scale robots in unstructured environments.\nIII-A\nSubstrate Preparation and Tracking Setup\nEach substrate was prepared in a transparent acrylic container (\n20\ncm\n20\\text{\\,}\\mathrm{cm}\nwide,\n30\ncm\n30\\text{\\,}\\mathrm{cm}\nlong,\n5\ncm\n5\\text{\\,}\\mathrm{cm}\ndeep) placed inside a light box (Fig.\n6\n). A GoPro Hero 12 Black mounted overhead on a fixed tripod provided top-down video for trajectory tracking, with rulers for scale calibration while tracking. All the substrates were leveled to a uniform depth of\n3\ncm\n3\\text{\\,}\\mathrm{cm}\nto ensure consistency across trials.\nIII-B\nSkipping on Various Substrates\nWe first evaluated skipping performance on substrates where fin based crawling is challenging such as sand, mud, and grass. Representative frames in Fig.\n7\nshow locomotion on bentonite clay powder (Pure original ingredients) mud with 1:3 water to clay powder ratio, non uniform desert sand (KolorScape, Paver sand step 2), uniform black aquarium sand (Imagitarium), and artificial grass (Grassclub). The trials were conducted with a fully charged battery, operating the robot at the maximum tail actuation frequency of\n1\nHz\n1\\text{\\,}\\mathrm{Hz}\nor 60 rpm. Motion was recorded at 60 fps and analyzed frame-by-frame to extract displacement and velocity using tracking software (Tracker, physlets.org/tracker/).\nFigure 7:\nSnapshots of TerraSkipper skipping on uniform aquarium sand, non uniform desert sand, bentonite clay powder mud, and artificial grass. These substrates highlight conditions where fin based crawling alone is ineffective or highly challenging.\nSubstrate\nMean skipping speed (\ncm\ns\n−\n1\n\\mathrm{cm}\\text{\\,}{\\mathrm{s}}^{-1}\n)\nUniform aquarium sand\n0.92\n±\n0.38\n0.92\\pm 0.38\nNon-uniform sand\n2.63\n±\n0.22\n2.63\\pm 0.22\nBentonite mud\n1.24\n±\n0.12\n1.24\\pm 0.12\nArtificial grass\n5.38\n±\n0.71\n5.38\\pm 0.71\nTABLE III:\nMean skipping velocities across different substrates with standard deviation for\nn\n=\n3\nn=3\ntrials.\nQuantitatively, skipping produced mean speeds of\n0.92\n±\n0.38\n0.92\\pm 0.38\ncm\ns\n−\n1\n\\mathrm{cm}\\text{\\,}{\\mathrm{s}}^{-1}\non uniform aquarium sand,\n2.63\n±\n0.22\n2.63\\pm 0.22\ncm\ns\n−\n1\n\\mathrm{cm}\\text{\\,}{\\mathrm{s}}^{-1}\non non-uniform desert sand,\n1.24\n±\n0.12\n1.24\\pm 0.12\ncm\ns\n−\n1\n\\mathrm{cm}\\text{\\,}{\\mathrm{s}}^{-1}\non bentonite mud, and\n5.38\n±\n0.71\n5.38\\pm 0.71\ncm\ns\n−\n1\n\\mathrm{cm}\\text{\\,}{\\mathrm{s}}^{-1}\non artificial grass (Table\nIII\n). The ordering (grass\n>\n>\nnon-uniform sand\n>\n>\nmud\n>\n>\nuniform sand) reflects how the substrate supports impulsive ground reaction: stiff grass and partially compacted sand transfer larger impulses, whereas loose granular beds such as uniform aquarium sand dissipate energy during tail impact.\nFigure 8:\nMean velocity vs. moisture content for three locomotion modes on (A) aquarium sand and (B) bentonite clay. Moisture is percent water by mass relative to dry substrate. Each point is the mean of three trials; error bars show the standard deviations across trials. Trials with displacements\n<\n10\ncm\n<$10\\text{\\,}\\mathrm{cm}$\nwere treated as failures.\nFigure 9:\nSide-view sequences of TerraSkipper in outdoor tests. Panels show (left to right): skipping on grass, skipping on sand, and synchronous crawling on hard ground. Frames are overlaid every\n6\ns\n6\\text{\\,}\\mathrm{s}\n; each panel displays\n6\ns\n6\\text{\\,}\\mathrm{s}\nof motion.\nIII-C\nEffect of Moisture Content\nIn the previous section, we demonstrated the viability of skipping locomotion on diverse substrates where fin driven crawling alone is limited. To further investigate how locomotor performance depends on substrate properties, we systematically varied the water content in selected materials and compared the resulting crawling and skipping behaviors. Two substrates were chosen for this study: (1) uniform black aquarium sand (Imagitarium) and (2) bentonite clay powder (Pure natural ingredients).\nFor sand, adding water alters the bulk mechanical response: dry sand behaves as a loose, frictional medium, while small amounts of water increase cohesion and improve footing, and higher contents lead to fluid-like behavior that reduces support. To prepare the test bed, we began with\n2\nkg\n2\\text{\\,}\\mathrm{kg}\nof dry black aquarium sand (\n0\n%\n0\\text{\\,}\\mathrm{\\char 37\\relax}\nwater by mass) and incrementally added\n100\nmL\n100\\text{\\,}\\mathrm{mL}\nof water per iteration, hand-mixing for\n10\nmin\n10\\text{\\,}\\mathrm{min}\nto ensure uniformity, corresponding to a\n5\n%\n5\\text{\\,}\\mathrm{\\char 37\\relax}\nincrease in water content. At each level, three trials were performed for synchronous crawling, asynchronous crawling, and skipping, and the mean velocities with standard deviations were plotted as shown in Fig.\n8\n-A.\nFig.\n8\n-A shows how skipping followed a bell-shaped trend: velocity was lowest on dry sand (\n0.4\ncm\ns\n−\n1\n0.4\\text{\\,}\\mathrm{cm}\\text{\\,}{\\mathrm{s}}^{-1}\n), peaked at\n3.4\ncm\ns\n−\n1\n3.4\\text{\\,}\\mathrm{cm}\\text{\\,}{\\mathrm{s}}^{-1}\nat\n15\n%\n15\\text{\\,}\\mathrm{\\char 37\\relax}\nwater, and declined beyond this point as the substrate water content increased. Crawling required cohesive packing to be effective. Both modes failed in dry sand, but asynchronous crawling improved gradually at\n5\n%\nto\n10\n%\n5\\text{\\,}\\mathrm{\\char 37\\relax}10\\text{\\,}\\mathrm{\\char 37\\relax}\nmoisture to\n2.7\ncm\ns\n−\n1\n2.7\\text{\\,}\\mathrm{cm}\\text{\\,}{\\mathrm{s}}^{-1}\n, while synchronous crawling reached its maximum of\n3.0\ncm\ns\n−\n1\n3.0\\text{\\,}\\mathrm{cm}\\text{\\,}{\\mathrm{s}}^{-1}\nat\n15\n%\n15\\text{\\,}\\mathrm{\\char 37\\relax}\n. Above\n20\n%\n20\\text{\\,}\\mathrm{\\char 37\\relax}\n, both crawling gaits declined in speed but remained more effective than in the dry state. Overall, skipping was the better locomotion mode compared to crawling, achieving mobility across the widest range of moisture levels and delivering the highest peak velocity.\nFor bentonite clay, adding water similarly changes the substrate response but with higher absorption capacity than sand. To prepare the test bed, we used\n500\ng\n500\\text{\\,}\\mathrm{g}\nof dry clay powder and added\n100\nmL\n100\\text{\\,}\\mathrm{mL}\nof water per iteration, hand mixing thoroughly for 10 minutes. This process allowed us to systematically increase the water content in increments while accounting for the material’s strong tendency to absorb and retain water. At each moisture level, three trials were performed for synchronous crawling, asynchronous crawling, and skipping, and the mean velocities were plotted (Fig.\n8\n-B).\nFig.\n8\n-B shows that skipping again outperformed crawling across different moisture content except at\n80\n%\n80\\text{\\,}\\mathrm{\\char 37\\relax}\nand\n100\n%\n100\\text{\\,}\\mathrm{\\char 37\\relax}\nmoisture content because of the tail slippage. In the dry state, locomotion was negligible, but performance improved steadily with added water, reaching a peak of about\n2.6\ncm\ns\n−\n1\n2.6\\text{\\,}\\mathrm{cm}\\text{\\,}{\\mathrm{s}}^{-1}\nat\n20\n%\n20\\text{\\,}\\mathrm{\\char 37\\relax}\nmoisture. Beyond this level, velocities declined as the clay transitioned from solid to a viscous slurry that dissipated energy and caused slip during locomotion. Crawling gaits followed a similar trend but at consistently lower velocities: asynchronous and synchronous crawling performed best around\n60\n%\n60\\text{\\,}\\mathrm{\\char 37\\relax}\nmoisture\n0.7\ncm\ns\n−\n1\n0.7\\text{\\,}\\mathrm{cm}\\text{\\,}{\\mathrm{s}}^{-1}\nand\n1.7\ncm\ns\n−\n1\n1.7\\text{\\,}\\mathrm{cm}\\text{\\,}{\\mathrm{s}}^{-1}\nrespectively. Overall, skipping proved to be the most effective gait on clay, maintaining forward mobility across a broad range of water contents and achieving the highest peak velocity.\nFailures (i.e., points with a mean velocity of\n0\ncm\ns\n−\n1\n0\\text{\\,}\\mathrm{cm}\\text{\\,}{\\mathrm{s}}^{-1}\n) were primarily due to (i) excavation and self-slippage into the substrate, which arrested forward motion, or (ii) pitching that lifted the forebody on firm ground and leaning on the tail, reducing contact and traction.\nIII-D\nOutdoor Demonstration\nWe tested TerraSkipper on natural outdoor terrains: grass, loose non uniform sand, and hard ground. Side-view time-lapse sequences are shown in Fig.\n9\n, with frames overlaid every\n6\ns\n6\\text{\\,}\\mathrm{s}\n. On grass and sand we used the skipping mode, because grass blades entangle the fins during crawling and the robot excavates into dry sand instead of advancing; consistent with section\nIII-C\n, synchronous and asynchronous crawling did not succeed on these substrates. In a continuous run, after\n12\ns\n12\\text{\\,}\\mathrm{s}\nthe robot reached firm ground, where we switched to synchronous crawling for the next\n6\ns\n6\\text{\\,}\\mathrm{s}\n. On hard ground, tail–ground interaction imposes minimal drag and does not impede forward progression (see Supplemental Video).\nThese results illustrate the benefit of switching locomotion modes in heterogeneous environments, impulsive skipping for compliant or entangling substrates, and crawling for firm terrain and highlight the effectiveness of the tail in natural settings.\nIV\nConclusion\nWe presented TerraSkipper, a centimeter-scale robot that blends fin based crawling (synchronous and asynchronous) with a springtail, impulsive skipping mechanism to traverse compliant and heterogeneous terrain with an average runtime of\n30\nmin\n30\\text{\\,}\\mathrm{min}\n. The fins are magnetically encoded with hall effect sensors to enable closed-loop gait timing; in contrast to open-loop operation. The feedback control yields stable straight-line trajectories with markedly reduced drift of less than\n1\ncm\n1\\text{\\,}\\mathrm{cm}\n. We also modeled and experimentally characterized the tail, identifying an optimal length that maximizes the averaged propulsive force of\n4\nN\n4\\text{\\,}\\mathrm{N}\nwith a maximum force of\n6\nN\n6\\text{\\,}\\mathrm{N}\n.\nWe further conducted systematic substrate trials to evaluate how moisture content and compaction influence locomotor performance. Skipping consistently enabled forward motion in conditions where crawling alone was ineffective and achieved the highest peak velocities on moderately cohesive substrates. Crawling gaits became viable only once sufficient cohesion developed, with synchronous and asynchronous patterns showing complementary advantages. These findings establish skipping as the more robust mode of locomotion across variable substrates.\nBeyond controlled laboratory tests, we validated the robot’s mobility in real-world environments. Outdoor demonstrations on natural grass, loose sand, and hard ground corroborated laboratory trends: skipping enabled progression on compliant or entangling substrates such as sand and grass where fin-driven crawling was ineffective, while synchronous crawling became advantageous on firm terrain. These results confirm that integrating impulsive tail actuation with fin-based control enables robust and versatile locomotion at small scales, and they motivate hybrid policies that adapt gait choice to substrate state.\nGoing forward, we see opportunities to (i) infer terrain class and slip from onboard inertial sensing (inertial measurement unit, IMU) to trigger closed-loop mode switching; (ii) develop algorithms that adapt the locomotion mode to local terrain rather than relying on teleoperation; and (iii) expand the field tests to evaluate design viability across diverse sites. These directions aim to broaden reliable centimeter-scale robot mobility and autonomy beyond the lab and into heterogeneous natural environments.\nReferences\n[1]\nR. Baines, S. K. Patiballa, J. Booth, L. Ramirez, T. Sipple, A. Garcia, F. Fish, and R. Kramer-Bottiglio\n(2022)\nMulti-environment robotic transitions through adaptive morphogenesis\n.\nNature\n610\n(\n7931\n),\npp. 283–289\n.\nCited by:\n§I\n,\n§I\n.\n[2]\nP. Birkmeyer, K. Peterson, and R. S. Fearing\n(2009)\nDASH: a dynamic 16g hexapedal robot\n.\nIn\n2009 IEEE/RSJ international conference on intelligent robots and systems\n,\npp. 2683–2689\n.\nCited by:\nTABLE I\n,\n§I\n.\n[3]\nG. Bledt, M. J. Powell, B. Katz, J. Di Carlo, P. M. Wensing, and S. Kim\n(2018)\nMit cheetah 3: design and control of a robust, dynamic quadruped robot\n.\nIn\n2018 IEEE/RSJ International Conference on Intelligent Robots and Systems (IROS)\n,\npp. 2245–2252\n.\nCited by:\n§I\n.\n[4]\nS. N. Boateng, S. Singh, M. Ugur, S. Wang, M. Kramer, I. Osei, O. Sobek, M. O. Martinez, F. Z. Temel, and L. H. Blumenschein\n(2024)\nHeterogenous collaboration: a new approach for search and rescue operations\n.\nIn\n2024 IEEE International Symposium on Safety Security Rescue Robotics (SSRR)\n,\npp. 142–147\n.\nCited by:\n§I\n.\n[5]\nX. Chen, J. Yu, Z. Wu, Y. Meng, and S. Kong\n(2018)\nToward a maneuverable miniature robotic fish equipped with a novel magnetic actuator system\n.\nIEEE Transactions on Systems, Man, and Cybernetics: Systems\n50\n(\n7\n),\npp. 2327–2337\n.\nCited by:\n§I\n.\n[6]\nA. Crespi, K. Karakasiliotis, A. Guignard, and A. J. Ijspeert\n(2013)\nSalamandra robotica ii: an amphibious robot to study salamander-like swimming and walking gaits\n.\nIEEE Transactions on Robotics\n29\n(\n2\n),\npp. 308–320\n.\nCited by:\n§I\n.\n[7]\nA. DeMario and J. Zhao\n(2018)\nDevelopment and analysis of a three-dimensional printed miniature walking robot with soft joints and links\n.\nJournal of Mechanisms and Robotics\n10\n(\n4\n),\npp. 041005\n.\nCited by:\nTABLE I\n,\n§I\n.\n[8]\nM. Dunbabin and L. Marques\n(2012)\nRobots for environmental monitoring: significant advancements and applications\n.\nIEEE Robotics & Automation Magazine\n19\n(\n1\n),\npp. 24–39\n.\nCited by:\n§I\n.\n[9]\nR. S. Fearing\n(2006)\nChallenges for efffective millirobots\n.\nIn\n2006 IEEE International Symposium on MicroNanoMechanical and Human Science\n,\npp. 1–5\n.\nCited by:\n§I\n.\n[10]\nN. Gravish and G. V. Lauder\n(2018)\nRobotics-inspired biology\n.\nJournal of Experimental Biology\n221\n(\n7\n),\npp. jeb138438\n.\nCited by:\n§I\n.\n[11]\nD. W. Haldane, K. C. Peterson, F. L. G. Bermudez, and R. S. Fearing\n(2013)\nAnimal-inspired design and aerodynamic stabilization of a hexapedal millirobot\n.\nIn\n2013 IEEE international conference on robotics and automation\n,\npp. 3279–3286\n.\nCited by:\nTABLE I\n,\n§I\n.\n[12]\nD. W. Haldane, J. K. Yim, and R. S. Fearing\n(2017)\nRepetitive extreme-acceleration (14-g) spatial jumping with salto-1p\n.\nIn\n2017 IEEE/RSJ International Conference on Intelligent Robots and Systems (IROS)\n,\npp. 3345–3351\n.\nCited by:\n§I\n.\n[13]\nA. M. Johnson, T. Libby, E. Chang-Siu, M. Tomizuka, R. J. Full, and D. E. Koditschek\n(2012)\nTail assisted dynamic self righting\n.\nIn\nAdaptive mobile robotics\n,\npp. 611–620\n.\nCited by:\n§I\n.\n[14]\nS. M. Kawano and R. W. Blob\n(2013)\nPropulsive forces of mudskipper fins and salamander limbs during terrestrial locomotion: implications for the invasion of land\n.\nIntegrative and comparative biology\n53\n(\n2\n),\npp. 283–294\n.\nCited by:\n§I\n.\n[15]\nC. Li, T. Zhang, and D. I. Goldman\n(2013)\nA terradynamics of legged locomotion on granular media\n.\nscience\n339\n(\n6126\n),\npp. 1408–1412\n.\nCited by:\n§I\n,\n§I\n,\n§I\n.\n[16]\nT. Libby, A. M. Johnson, E. Chang-Siu, R. J. Full, and D. E. Koditschek\n(2016)\nComparative design, scaling, and control of appendages for inertial reorientation\n.\nIEEE Transactions on Robotics\n32\n(\n6\n),\npp. 1380–1398\n.\nCited by:\n§I\n.\n[17]\nZ. Lin, W. Zheng, J. Zhang, W. Ou, C. Yang, H. Huang, W. Xu, Z. Yang, W. Zhou, and Y. Zhang\n(2023)\nMudskipper-inspired amphibious robotic fish enhances locomotion performance by pectoral-caudal fins coordination\n.\nCell Reports Physical Science\n4\n(\n10\n).\nCited by:\n§I\n.\n[18]\nS. Longo, S. Cox, E. Azizi, M. Ilton, J. Olberding, R. St Pierre, and S. Patek\n(2019)\nBeyond power amplification: latch-mediated spring actuation is an emerging framework for the study of diverse elastic systems\n.\nJournal of Experimental Biology\n222\n(\n15\n),\npp. jeb197889\n.\nCited by:\n§\nII-B\n.\n[19]\nR. D. Maladen, Y. Ding, P. B. Umbanhowar, A. Kamor, and D. I. Goldman\n(2011)\nMechanical models of sandfish locomotion reveal principles of high performance subsurface sand-swimming\n.\nJournal of The Royal Society Interface\n8\n(\n62\n),\npp. 1332–1345\n.\nCited by:\n§I\n.\n[20]\nR. R. Murphy\n(2017)\nDisaster robotics\n.\nMIT press\n.\nCited by:\n§I\n.\n[21]\nC. Pace and A. Gibb\n(2009)\nMudskipper pectoral fin kinematics in aquatic and terrestrial environments\n.\nJournal of Experimental Biology\n212\n(\n14\n),\npp. 2279–2286\n.\nCited by:\n§I\n.\n[22]\nF. Ramirez Serrano, N. P. Hyun, E. Steinhardt, P. Lechère, and R. J. Wood\n(2025)\nA springtail-inspired multimodal walking-jumping microrobot\n.\nScience Robotics\n10\n(\n99\n),\npp. eadp7854\n.\nCited by:\n§I\n.\n[23]\nU. Saranli, M. Buehler, and D. E. Koditschek\n(2001)\nRHex: a simple and highly mobile hexapod robot\n.\nThe International Journal of Robotics Research\n20\n(\n7\n),\npp. 616–631\n.\nCited by:\n§I\n.\n[24]\nS. Singh, Z. Temel, and R. S. Pierre\n(2024)\nMulti-modal jumping and crawling in an autonomous, springtail-inspired microrobot\n.\nIn\n2024 IEEE International Conference on Robotics and Automation (ICRA)\n,\npp. 5999–6005\n.\nCited by:\n§I\n.\n[25]\nS. Singh, R. Truax, and R. S. Pierre\n(2024)\nBuffalo byte: a highly mobile and autonomous millirobot platform\n.\nIEEE Robotics and Automation Letters\n9\n(\n5\n),\npp. 4067–4074\n.\nCited by:\nTABLE I\n,\n§I\n.\n[26]\nR. St.Pierre and S. Bergbreiter\n(2019)\nToward autonomy in sub-gram terrestrial robots\n.\nAnnual Review of Control, Robotics, and Autonomous Systems\n2\n,\npp. 231–252\n.\nCited by:\n§I\n.\n[27]\nJ. Sun, E. Lerner, B. Tighe, C. Middlemist, and J. Zhao\n(2023)\nEmbedded shape morphing for morphologically adaptive robots\n.\nNature communications\n14\n(\n1\n),\npp. 6023\n.\nCited by:\n§I\n.\n[28]\nS. M. Trenkwalder\n(2019)\nComputational resources of miniature robots: classification and implications\n.\nIEEE Robotics and Automation Letters\n4\n(\n3\n),\npp. 2722–2729\n.\nCited by:\n§\nII-C\n.\n[29]\nT. S. Vaquero, G. Daddi, R. Thakker, M. Paton, A. Jasour, M. P. Strub, R. M. Swan, R. Royce, M. Gildner, P. Tosi,\net al.\n(2024)\nEELS: Autonomous snake-like robot with task and motion planning capabilities for ice world exploration\n.\nScience Robotics\n9\n(\n88\n),\npp. eadh8332\n.\nCited by:\n§I\n,\n§I\n.\n[30]\nY. Yang, J. Norby, J. K. Yim, and A. M. Johnson\n(2023)\nProprioception and tail control enable extreme terrain traversal by quadruped robots\n.\nIn\n2023 IEEE/RSJ International Conference on Intelligent Robots and Systems (IROS)\n,\npp. 735–742\n.\nCited by:\n§I\n.\n[31]\nT. Zhang and D. I. Goldman\n(2014)\nThe effectiveness of resistive force theory in granular locomotion\n.\nPhysics of Fluids\n26\n(\n10\n).\nCited by:\n§I\n.",
    "preview_text": "Mudskippers are unique amphibious fish capable of locomotion in diverse environments, including terrestrial surfaces, aquatic habitats, and highly viscous substrates such as mud. This versatile locomotion is largely enabled by their powerful tail, which stores and rapidly releases energy to produce impulsive jumps. Inspired by this biological mechanism, we present the design and development of a multi-terrain centimeter-scale skipping and crawling robot. The robot is predominantly 3D printed and features onboard sensing, computation, and power. It is equipped with two side fins for crawling, each integrated with a hall effect sensor for gait control, while a rotary springtail driven by a 10mm planetary gear motor enables continuous impulsive skipping across a range of substrates to achieve multi-terrain locomotion. We modeled and experimentally characterized the tail, identifying an optimal length of 25mm that maximizes the mean propulsive force (4N, peaks up to 6N) for forward motion. In addition, we evaluated skipping on substrates where fin based crawling alone fails, and varied the moisture content of uniform sand and bentonite clay powder to compare skipping with crawling. Skipping consistently produced higher mean velocities than crawling, particularly on viscous and granular media. Finally, outdoor tests on grass, loose sand, and hard ground confirmed that combining skipping on entangling and granular terrain with crawling on firm ground extends the operational range of the robot in real-world environments.\n\nTerraSkipper: A Centimeter-Scale Robot for Multi-Terrain Skipping and Crawling\nShashwat Singh\n1\n, Sheri Zhang\n1,2\n, Spencer Matonis\n3\n, and Zeynep Temel\n1\nThis work is supported in part by National Science Foundation grants 2308654.\n1\nThe Robotics Institute, Carnegie Mellon University, Pittsburgh, PA 15213, USA.\n2\nDepartment of Mechanical Engineering, Carnegie Mellon University, Pittsburgh, PA 15213, USA.\n3\nEdulis Therapeutics, Nashville, TN 37204.Corresp",
    "is_relevant": false,
    "relevance_score": 1.0,
    "extracted_keywords": [
        "locomotion"
    ],
    "one_line_summary": "这篇论文介绍了一种受弹涂鱼启发的厘米级多地形跳跃和爬行机器人，主要关注机械设计、实验表征和户外测试，与强化学习、VLA等关键词基本无关。",
    "detailed_summary": "",
    "qa_pairs": [],
    "is_hidden": false,
    "is_starred": false,
    "flag": true,
    "published_date": "2026-03-29T14:59:42Z",
    "created_at": "2026-04-07T15:55:42.385599",
    "updated_at": "2026-04-07T15:55:42.385607"
}