{
    "id": "2605.12654v1",
    "title": "COSMIC: Concurrent Optimization of Structure, Material, and Integrated Control for robotic systems",
    "authors": [
        "Qinsong Guo",
        "Liwei Wang"
    ],
    "abstract": "复制并超越自然生物的自主性一直是机器人学领域的长远目标。然而，现有大多数机器人系统的结构、材料和控制策略是分步设计的，这与自然界中的协同进化形成了鲜明对比。这种设计分离常导致次优方案，我们至今仍对设计要素的个体贡献与协同作用缺乏深入理解。本研究提出了一种基于梯度的协同设计框架，可同步优化桁架晶格机器人拓扑结构、材料分布与控制策略。该框架将混合型拓扑变量与材料变量嵌入连续设计空间，在可微分仿真器中集成神经网络控制器，通过捕捉各要素交互关系并利用自动微分实现高效梯度计算。此外，我们开发了约束优化方法以应对高度非凸的设计空间，实现所有设计要素的联合优化。案例研究表明，该框架能持续生成超越分离设计基线的多样化运动策略，并灵活适配不同功能需求与边界条件。通过该框架，我们进一步提取出揭示设计要素对机器人性能个体及协同影响规律的设计洞察。该框架为具备重构、运动及其他复杂自主行为的机器人系统自主协同设计提供了计算基础。",
    "url": "https://arxiv.org/abs/2605.12654v1",
    "html_url": "https://arxiv.org/html/2605.12654v1",
    "html_content": "COSMIC: Concurrent Optimization of Structure, Material, and Integrated Control for robotic systems\nQinsong Guo\nDept. of Mechanical Engineering\nCarnegie Mellon University\nPittsburgh, PA 15213\ntimg@andrew.cmu.edu\n&\nLiwei Wang\nDept. of Mechanical Engineering\nCarnegie Mellon University\nPittsburgh, PA 15213\nliweiw@andrew.cmu.edu\nCorresponding author\nAbstract\nReplicating and surpassing the autonomy of natural organisms remains a long-standing goal in robotics. Yet most robotic systems have their structure, materials, and control designed separately, in sharp contrast to the co-evolution in nature. This separation often leads to suboptimal designs, and we still have a limited understanding of the individual and collective contributions of these design entities. In this work, we propose a gradient-based co-design framework that simultaneously optimizes the topology, material distribution, and control policy of a truss-lattice robot. The framework embeds mixed-type topological and material variables into a continuous design space and integrates a neural network controller within a differentiable simulator, capturing their interactions and enabling efficient gradient calculation via automatic differentiation. Furthermore, we develop a constrained optimization to navigate the highly non-convex design landscape and jointly optimize all design entities. Case studies demonstrate that the proposed framework consistently discovers diverse locomotion strategies that outperform baselines obtained through separated design. The framework is also flexible to accommodate different functional requirements and boundary conditions. Using this framework, we further extract design insights that reveal the individual and collective effects of different entities on robotic performance. The proposed framework provides a computational foundation for the autonomous co-design of robotic systems, capable of reconfiguration, locomotion, and other complex autonomous behaviors.\nKeywords\nco-design\n⋅\n\\cdot\ntopology optimization\n⋅\n\\cdot\ndifferentiable simulation\n⋅\n\\cdot\nmachine learning\n1\nIntroduction\nRobots, and machines more broadly, originate from our aspiration to reproduce the autonomy observed in humans and animals, and ultimately surpass natural capabilities\nFu\net al.\n(\n2014\n)\n. To date, substantial progress has been achieved in several key components of robotic systems, i.e., structure\nZhang\net al.\n(\n2025\n)\n, materials\nKotikian\net al.\n(\n2018\n); Zhang\net al.\n(\n2024\n)\n, and control\nGu\net al.\n(\n2025\n); Aguilar\net al.\n(\n2016\n)\n. However, autonomous robots remain far less adaptive and diverse compared with their natural counterparts\nBaines\net al.\n(\n2024\n)\n. While advances in soft robotics and responsive materials have expanded the design space\nKotikian\net al.\n(\n2018\n); Zhang\net al.\n(\n2024\n)\n, robot morphologies remain far narrower than the vast diversity found in nature. More fundamentally, structure, materials, and control are often designed separately or sequentially, rather than being co-designed in a tightly coupled manner\nZhang\net al.\n(\n2025\n); Gu\net al.\n(\n2025\n); Kobayashi\net al.\n(\n2024\n); Howard\net al.\n(\n2019\n); Schulz\net al.\n(\n2017\n); Spinos and Yim (\n2022\n)\n. For example, a robot structure is typically first specified, after which control strategies are developed to operate the resulting body\nGuan\net al.\n(\n2023\n); van Diepen and Shea (\n2022\n)\n. This contrasts with natural systems, where structure, material, and control strategies coevolve to produce highly diverse and specialized organisms\nBertossa (\n2011\n)\n.\nMotivated by this observation, there is growing interest in exploring whether the co-design can lead to performance improvements and increased diversity in artificial robotic systems\nMatthews\net al.\n(\n2023\n)\n. This interest in co-design is supported by two considerations. First, from a physical perspective, structure, materials, and control are inherently coupled in system dynamics, producing collective effects that cannot be achieved by each entity independently. Second, from a design perspective, co-design greatly expands the design space\nLi\net al.\n(\n2024\n)\n, which is more likely to contain a superior optima that is inaccessible to separated design pipelines.\nYet, obtaining an optimal solution via co-design remains challenging in practice. First, the design of different entities often requires variables of different types, leading to a massive and sometimes combinatorial design space. Second, evaluating a robot’s dynamic performance is difficult and computationally expensive, involving contacts, friction, large deformations, and nonlinear material behavior\nArmanini\net al.\n(\n2023\n); Kumar\net al.\n(\n2018\n)\n. This often requires small integration steps over long time horizons, making exhaustive searches prohibitively costly. Although advanced evolutionary algorithms\nLi\net al.\n(\n2024\n); Kriegman\net al.\n(\n2020\n); Karacakol\net al.\n(\n2025\n); Strgar and Kriegman (\n2025\n); Strgar\net al.\n(\n2024\n); Bhattacharyya\net al.\n(\n2023\n)\nand dimensionality-reduction techniques\nSchaff\net al.\n(\n2022\n); Wang\net al.\n(\n2023a\n)\nenable more effective search, they still require large populations and many iterations to converge. Third, the physical coupling across design entities makes the underlying optimization problem highly non-convex, even discontinuous; for instance, small changes to structure may lead to large and unpredictable changes in performance. Consequently, comprehensive co-design has mainly been demonstrated for quasi-static systems, such as shape-morphing material networks\nWang\net al.\n(\n2025\n)\n, kirigami\nBordiga\net al.\n(\n2024\n)\n, and granular matter\nParsa\net al.\n(\n2024\n)\n, which are computationally cheaper to evaluate with smoother objectives.\nRecent pioneering efforts have begun extending co-design to dynamic systems\nJiang\net al.\n(\n2016\n); Wang\net al.\n(\n2023b\n); Davy\net al.\n(\n2023\n); Spielberg\net al.\n(\n2023\n); Newbury\net al.\n(\n2024\n)\n. In particular, GPU-parallel physics solvers dramatically accelerate evaluations\nXue\net al.\n(\n2023\n); Hu\net al.\n(\n2020\n)\n, while auto-differentiation\nDu\net al.\n(\n2021\n); Jia\net al.\n(\n2024\n)\nenables efficient calculation of gradients over long temporal horizons for design variables, even in the presence of discontinuous contacts. These advances have enabled a range of frameworks that achieve co-design using gradient-based optimization, drastically reducing the number of simulations compared with exhaustive or heuristic optimizers\nMatthews\net al.\n(\n2023\n); Spielberg\net al.\n(\n2023\n); Sato\net al.\n(\n2025\n); Yuhn\net al.\n(\n2023\n); Ma\net al.\n(\n2021\n)\n. Many of these approaches focus on continuum soft robots\nWang\net al.\n(\n2023b\n); Spielberg\net al.\n(\n2019\n); Wang (\n2025\n); Bhattacharyya\net al.\n(\n2023\n)\n, which allow continuous variations in structures and materials and therefore enable stable optimization\nKobayashi\net al.\n(\n2024\n); Yuhn\net al.\n(\n2023\n)\n. In contrast, co-design of discrete robotic systems remains relatively limited. Their discrete nature introduces mixed-variable design space, sharp discontinuities, and severe nonconvexity in the optimization landscape, making gradient-based co-design more challenging\nLumpe and Shea (\n2023\n)\n. Yet such systems have many important applications, including legged robots\nDinev\net al.\n(\n2022\n); Gao\net al.\n(\n2023\n)\n, tensegrity structures\nCaluwaerts\net al.\n(\n2014\n); Shah\net al.\n(\n2022\n)\n, and bio-hybrid robots\nKinjo\net al.\n(\n2024\n); Webster-Wood\net al.\n(\n2022\n)\n. Therefore, despite these pioneering efforts, there remains a need for comprehensive gradient-based platforms that enable the co-design of structure, materials, and control, particularly for discrete robotic systems. Furthermore, we still lack a clear understanding of the individual and collective contributions of different design entities to the system-level performance\nWang (\n2025\n); Zhao and Zhang (\n2022\n)\n.\nIn this work, we propose a framework that co-designs the structure, material layout, and control of a discrete truss-lattice robot (Fig.\n1\n). We begin by constructing a unified spatial-temporal design space, merging structure and material selections with control neural network training (Fig.\n1\na). We then develop a GPU-enabled differentiable dynamic simulation to quantify system performance and sensitivity (Fig.\n1\nb). We integrate the representation and differentiable evaluation into a constrained optimization to iteratively and concurrently update all design entities (Fig.\n1\nc). The framework is demonstrated for a range of dynamic tasks, uncovering valuable knowledge on the effects of co-design entities (Fig.\n1\nd).\nOur proposed framework has the following contributions:\n•\nWe introduce a continuous, differentiable design representation that unifies spatial topological, discrete material selection, and spatiotemporal neural control in a discrete robot, enabling the use of efficient gradient-based optimization.\n•\nWe develop a GPU-parallel differentiable simulator that captures the physical interdependency among design entities and their environment, efficiently evaluating dynamics in contact-rich scenarios while providing gradient information through automatic differentiation.\n•\nWe propose a constrained optimization method that jointly designs structure, materials, and control to automate dynamic robot design. The method incorporates mechanisms to ensure structural integrity and physical feasibility, and automatically generates robotic designs for customized tasks that outperform conventional separate design strategies.\n•\nWe uncover important design insights by revealing the individual and collective effects of structures, materials, and control on system-level performance.\nThe remainder of this paper is structured as follows. We first detail the proposed co-design framework (Section\n2\n), and then demonstrate its effectiveness against baselines (Section\n3.1\n). Next, we employ an ablation study to investigate the individual and collective contributions of design entities (Section\n3.2\n). Finally, we demonstrate the generalizability of the framework across different objectives, physical environments, and design spaces (Section\n3.3\n). Conclusions are drawn in Section\n4\n.\nFigure 1:\nOverview of the dynamic co-design platform\n2\nMethod\nIn this section, we develop a general co-design framework for dynamic robotic systems. We consider a lattice robot composed of truss elements, where each truss can function either as a passive skeleton or as an externally controlled actuator. Our goal is to co-design the topology, the spatial distribution of material types, and the temporal control signals for each actuator to maximize dynamic performance. To achieve this, we extend topology optimization to integrate a mixed-variable design representation, a differentiable dynamic simulation for design evaluation, and a constrained optimization for design synthesis.\n2.1\nDesign Representation\n2.1.1\nTopology and Material Layout\nFigure 2:\nDesign representation: (a) Each edge\nE\ni\n​\nj\nE_{ij}\nis associated with a continuous, relaxed design vector\n𝐳\ni\n​\nj\n\\mathbf{z}_{ij}\n. (b) Through a softmax projection scaled by\nβ\n\\beta\n, (c) we project it to a one-hot-encoded material state vector\n𝐳\n~\ni\n​\nj\n\\mathbf{\\tilde{z}}_{ij}\n, that dictates the mix ratio between discrete material types. (d) The Multi-Layer Perceptron controller receives synchronized clock signals from a Central Pattern Generator, the instantaneous nodal positional offsets and velocity, and a 2D goal vector to (e) output a control signal for each edge\nu\ni\n​\nj\n​\n(\nt\n)\n∈\n[\n−\n1\n,\n1\n]\nu_{ij}(t)\\in[-1,1]\n. (f) The control signal is scaled by edge material properties, including\na\nmax\na_{\\max}\nand\nz\n~\ni\n​\nj\n,\n3\n\\tilde{z}_{ij,3}\nto yield the target strain for each edge at time\nt\nt\n,\nϵ\ntarget\n,\ni\n​\nj\n​\n(\nt\n)\n\\epsilon_{\\text{target},{ij}}(t)\n. Notice how only edges with the actuator material state have non-zero target strain.\nConsider a lattice robot composed of truss elements connected at mass nodes, as shown in Fig.\n2\n. The structure can be represented as a graph with\nN\nm\nN_{m}\nnodes and\nN\ne\nN_{e}\nedges\nE\ni\n​\nj\nE_{ij}\n, where each edge connects node\ni\ni\nand node\nj\nj\n. The set of all connected node pairs is denoted by\nE\n=\n{\n(\ni\n,\nj\n)\n}\nE=\\{(i,j)\\}\n. Each edge can take one of three possible states: void, skeleton, and actuator. To represent this edge-wise design choice, we associate each edge\nE\ni\n​\nj\nE_{ij}\nwith a three-dimensional one-hot vector\n𝐳\ni\n​\nj\n=\n[\nz\ni\n​\nj\n,\n1\n,\nz\ni\n​\nj\n,\n2\n,\nz\ni\n​\nj\n,\n3\n]\n⊤\n∈\n{\n0\n,\n1\n}\n3\n\\mathbf{z}_{ij}=[z_{ij,1},z_{ij,2},z_{ij,3}]^{\\top}\\in\\{0,1\\}^{3}\n, where the three entries correspond to the states void, skeleton, and actuator, respectively (Figure\n2\nc). When an edge is assigned a specific state, the corresponding entry equals one while the others are zero. This discrete representation poses challenges for gradient-based optimization. Therefore, we relax the design variable to a continuous vector\n𝐳\ni\n​\nj\n∈\n[\n0\n,\n1\n]\n3\n\\mathbf{z}_{ij}\\in[0,1]^{3}\n(Figure\n2\na) and project it to a normalized material state vector\n𝐳\n~\ni\n​\nj\n\\mathbf{\\tilde{z}}_{ij}\nusing a scaled softmax function that approximates the original one-hot encoding:\nz\n~\ni\n​\nj\n,\nk\n=\nexp\n⁡\n(\nβ\n​\nz\ni\n​\nj\n,\nk\n)\n∑\nl\n=\n1\n3\nexp\n⁡\n(\nβ\n​\nz\ni\n​\nj\n,\nl\n)\n,\n\\tilde{z}_{ij,k}=\\frac{\\exp(\\beta z_{ij,k})}{\\sum_{l=1}^{3}\\exp(\\beta z_{ij,l})},\n(1)\nwhere\nβ\n\\beta\nis a scaling factor to control the projection sharpness, as shown in Figure\n2\nb. To further promote binarization, we introduce an explicit binarization constraint in the optimization problem (Section.\n2.3\n), which can adaptively penalize intermediate values to drive the design variables toward one-hot encodings that correspond to discrete material states.\nTo interface with the physical simulation, each material state is associated with\nH\nH\nmechanical properties, stored in a material property library matrix\nΨ\n∈\nℝ\nN\ne\n×\nH\n\\Psi\\in\\mathbb{R}^{N_{e}\\times H}\n. The effective property vector\n𝐩\ni\n​\nj\n∈\nℝ\nH\n\\mathbf{p}_{ij}\\in\\mathbb{R}^{H}\nfor truss\nE\ni\n​\nj\nE_{ij}\nis computed via matrix multiplication:\n𝐩\ni\n​\nj\n=\nΨ\n⊤\n​\n𝐳\ni\n​\nj\n,\n\\mathbf{p}_{ij}=\\Psi^{\\top}\\mathbf{z}_{ij},\n(2)\nwhere the entries of\n𝐩\ni\n​\nj\n\\mathbf{p}_{ij}\ndictate the interpolated mechanical properties (e.g., stiffness, density) to be used in simulation.\nIn this study, we consider\nH\n=\n3\nH=3\nproperties in the property matrix\nΨ\n\\Psi\n, including the stiffness (\nk\n), linear density (\nρ\n\\rho\n), and maximum actuation strain (\na\nmax\na_{\\max}\n). Each material state is characterized by a distinct combination of these properties:\n•\nVoid (\nV\nV\n):\nhas ultra-low stiffness, ultra-low linear density, and zero actuation capability. Trusses assigned to this state effectively act as a void to allow topological changes.\n•\nSkeleton (\nS\nS\n):\nhas high stiffness, medium density, and zero actuation capability. It mainly provides the structural support of the robot. Its high stiffness allows it to passively resist deformation, upholding the structural integrity vital for the stability of a discrete lattice.\n•\nActuator (\nA\nA\n):\nhas a stiffness an order of magnitude lower than the skeleton, and a linear density three times as high (mirroring the heavy weight of real-world electromechanical components). While compliant and heavy, it possesses high actuation capabilities.\nThis property scheme reflects the inherent trade-off observed in natural and artificial systems, where a truss cannot simultaneously possess high stiffness and high actuation capacity. Therefore, to maximize performance within a limited materials constraint, it requires a highly strategic, synergistic allocation of passive skeleton and active actuation.\nFinally, to accelerate the simulation, we lump the mass of the trusses at the connecting nodes. The mass\nm\ni\nm_{i}\nof node\ni\ni\nis computed as:\nm\ni\n=\nm\nϵ\n+\n1\n2\n​\n∑\nj\n∈\n𝒩\n​\n(\ni\n)\nl\ni\n​\nj\n​\n∑\nk\n=\n1\n3\nz\n~\ni\n​\nj\n,\nk\n​\nρ\nk\n,\nm_{i}=m_{\\epsilon}+\\frac{1}{2}\\sum_{j\\in\\mathcal{N}(i)}l_{ij}\\sum_{k=1}^{3}\\tilde{z}_{ij,k}\\rho_{k},\n(3)\nwhere\n𝒩\n​\n(\ni\n)\n\\mathcal{N}(i)\ndenotes the set of nodes connected to node\ni\ni\n,\nl\ni\n​\nj\nl_{ij}\nis the resting length of edge\nE\ni\n​\nj\nE_{ij}\n, and\nρ\nk\n\\rho_{k}\nis the linear density associated with material state\nk\nk\n. To maintain numerical stability and prevent singularities during the physics simulation, every node is initialized with a negligible baseline mass\nm\nϵ\nm_{\\epsilon}\n. Consequently, nodes connected exclusively to void trusses act as negligible masses, naturally eliminating themselves from the system dynamics. The head node\ni\n=\n0\ni=0\nis instantiated with a larger weight, acting as a payload to be carried forth by the robot.\n2.1.2\nActuation Control\nThe dynamic actuation of the robot is governed by a Multi-Layer Perceptron (MLP) neural network, as shown in Figure\n2\nd. The MLP processes the instantaneous kinematic state of the robot alongside a synchronized clock signal to output a target actuation length for each truss. Specifically, the network input vector\n𝐈\n​\n(\nt\n)\n\\mathbf{I}(t)\nat time\nt\nt\nconsists of Central Pattern Generator (CPG) signals\nIjspeert (\n2008\n)\n, nodal positional offsets, nodal velocity vectors, and a goal position vector. The CPG signals\n𝐂\n​\n(\nt\n)\n∈\nℝ\nN\nCPG\n\\mathbf{C}(t)\\in\\mathbb{R}^{N_{\\text{CPG}}}\nare modeled as phase-shifted sine waves to ensure all active trusses actuate in a synchronized, periodic manner:\nC\nj\n​\n(\nt\n)\n=\nsin\n⁡\n(\nω\n​\nt\n+\n2\n​\nπ\n​\nj\nN\nCPG\n)\n,\nj\n∈\n{\n0\n,\n…\n,\nN\nCPG\n−\n1\n}\nC_{j}(t)=\\sin\\left(\\omega t+\\frac{2\\pi j}{N_{\\text{CPG}}}\\right),\\quad j\\in\\{0,\\dots,N_{\\text{CPG}}-1\\}\n(4)\nLet the position vector of node\ni\ni\nbe defined as\n𝐱\ni\n​\n(\nt\n)\n=\n[\nx\ni\n​\n(\nt\n)\n,\ny\ni\n​\n(\nt\n)\n]\n⊤\n\\mathbf{x}_{i}(t)=[x_{i}(t),y_{i}(t)]^{\\top}\n. The positional offsets are thus\nΔ\n​\n𝐱\ni\n​\n(\nt\n)\n\\Delta\\mathbf{x}_{i}(t)\n, which provide spatial awareness by tracking the displacement of each node\ni\n∈\nℳ\ni\\in\\mathcal{M}\nrelative to the geometric center of the robot:\nΔ\n​\n𝐱\ni\n​\n(\nt\n)\n=\n𝐱\ni\n​\n(\nt\n)\n−\n1\nN\nm\n​\n∑\nj\n=\n1\nN\nm\n𝐱\nj\n​\n(\nt\n)\n\\Delta\\mathbf{x}_{i}(t)=\\mathbf{x}_{i}(t)-\\frac{1}{N_{m}}\\sum_{j=1}^{N_{m}}\\mathbf{x}_{j}(t)\n(5)\nAdditionally, we define a 2D goal vector\n𝐱\ngoal\n∈\nℝ\n2\n\\mathbf{x}_{\\text{goal}}\\in\\mathbb{R}^{2}\nthat specifies the desired target coordinates for the robot’s locomotion.\nBy concatenating these features, we obtain the complete input vector:\n𝐈\n​\n(\nt\n)\n=\n[\n𝐂\n​\n(\nt\n)\n⊤\n,\n𝐱\ngoal\n,\nΔ\n​\n𝐱\n1\n​\n(\nt\n)\n⊤\n,\n…\n,\nΔ\n​\n𝐱\nN\nm\n​\n(\nt\n)\n⊤\n,\n𝐯\n1\n​\n(\nt\n)\n⊤\n,\n…\n,\n𝐯\nN\nm\n​\n(\nt\n)\n⊤\n]\n⊤\n\\mathbf{I}(t)=\\left[\\mathbf{C}(t)^{\\top},\\mathbf{x}_{\\text{goal}},\\Delta\\mathbf{x}_{1}(t)^{\\top},\\dots,\\Delta\\mathbf{x}_{N_{m}}(t)^{\\top},\\mathbf{v}_{1}(t)^{\\top},\\dots,\\mathbf{v}_{N_{m}}(t)^{\\top}\\right]^{\\top}\n(6)\nWhile the CPG provides the fundamental gait frequency, positional and velocity information allows the control policy to be modulated by the gait cycle’s current stage, helping it react to environmental perturbations by sensing velocity changes. Further, the inclusion of the goal vector enabled active steering toward different spatial targets.\nThe MLP comprises a single hidden layer with a bias vector, followed by an output layer of dimension\nN\ne\nN_{e}\n, i.e., the total number of edges. We utilize a hyperbolic tangent (\ntanh\n\\tanh\n) activation function to bound the network outputs\nu\ni\n​\nj\n​\n(\nt\n)\n∈\n[\n−\n1\n,\n1\n]\nu_{ij}(t)\\in[-1,1]\n, where\n1\n1\ndenotes maximum extension and\n−\n1\n-1\ndenotes maximum contraction (Figure\n2\ne). While the control neural network outputs signals for all edges, only those edges assigned to the actuator state physically respond. To enforce this, we modulate the raw MLP outputs based on edge-wise material state vector to obtain the effective target strain\nϵ\ntarget\n,\ni\n​\nj\n​\n(\nt\n)\n\\epsilon_{\\text{target},{ij}}(t)\nas:\nϵ\ntarget\n,\ni\n​\nj\n​\n(\nt\n)\n=\nz\n~\ni\n​\nj\n,\n3\n⋅\na\nmax\n⋅\nu\ni\n​\nj\n​\n(\nt\n)\n,\n\\epsilon_{\\text{target},{ij}}(t)=\\tilde{z}_{ij,3}\\cdot a_{\\max}\\cdot u_{ij}(t),\n(7)\nwhere\nz\n~\ni\n​\nj\n,\n3\n\\tilde{z}_{ij,3}\nis the assigned ratio of Actuator for truss\nE\ni\n​\nj\nE_{ij}\n.\nThis way, only trusses in actuator states will receive a target strain (Figure\n2\nd).\n2.2\nDesign Evaluation\nFigure 3:\nIllustration of the differentiable simulation. At integration time\nt\nt\n, (a) a generalized Hooke’s law is used to determine the force produced by edge\nE\ni\n​\nj\nE_{ij}\nfrom its target actuation length\nl\ntarget\n,\ni\n​\nj\n​\n(\nt\n)\nl_{\\text{target},ij}(t)\nand current length\nl\ni\n​\nj\n​\n(\nt\n)\nl_{ij}(t)\n. (b) The pre-collision velocity vector\n𝐯\ni\n∗\n​\n(\nt\n)\n\\mathbf{v}^{*}_{i}(t)\nis calculated from the resultant aggregated force on node\ni\ni\nto update the nodal position\n𝐱\ni\n​\n(\nt\n+\nΔ\n​\nt\n)\n\\mathbf{x}_{i}(t+\\Delta t)\n. (c) The position and velocity of nodes that penetrate the ground are modified using Time Of Impact (TOI) techniques. At TOI, we compute a post-collision velocity vector\n𝐯\ni\n+\n​\n(\nt\n)\n\\mathbf{v}^{+}_{i}(t)\nby applying frictional damping to the pre-collision tangential component, and eliminating the perpendicular component. (d) Final nodal positions are obtained, advancing the simulation to the next step\nt\n+\nΔ\n​\nt\nt+\\Delta t\n, completing a forward simulation. Gradients are computed by propagating backwards in the computational graph (dashed arrows).\nWe further couple the proposed design representation with differentiable simulators to evaluate the system performance. We assume truss forces are governed by a generalized Hooke’s law, with stiffness and actuation properties computed in Eq.\n2\n. For example, the effective stiffness\nk\ni\n​\nj\n\\text{k}_{ij}\nof truss\nE\ni\n​\nj\nE_{ij}\nis computed as the dot product of its material state vector and the stiffness values associated with each state:\nk\ni\n​\nj\n=\nz\n~\ni\n​\nj\n,\n1\n​\nk\n1\n+\nz\n~\ni\n​\nj\n,\n2\n​\nk\n2\n+\nz\n~\ni\n​\nj\n,\n3\n​\nk\n3\n\\text{k}_{ij}=\\tilde{z}_{ij,1}\\text{k}_{1}+\\tilde{z}_{ij,2}\\text{k}_{2}+\\tilde{z}_{ij,3}\\text{k}_{3}\n.\nThe target actuation length of the truss is determined dynamically by the target strain\nϵ\ntarget\n,\ni\n​\nj\n​\n(\nt\n)\n\\epsilon_{\\text{target},ij}(t)\ngenerated by the MLP controller:\nl\ntarget\n,\ni\n​\nj\n​\n(\nt\n)\n=\nl\n0\n,\ni\n​\nj\n​\n[\n1\n+\nϵ\ntarget\n,\ni\n​\nj\n​\n(\nt\n)\n]\n,\nl_{\\text{target},ij}(t)=l_{0,ij}\\left[1+\\epsilon_{\\text{target},ij}(t)\\right],\n(8)\nwhere\nl\n0\n,\ni\n​\nj\nl_{0,ij}\nis the original length of the truss without actuation, as shown in Figure\n3\na. The internal scalar forces can then be calculated by Hooke’s law:\nF\ni\n​\nj\n​\n(\nt\n)\n=\nk\ni\n​\nj\n​\n[\nl\ni\n​\nj\n​\n(\nt\n)\n−\nl\ntarget\n,\ni\n​\nj\n​\n(\nt\n)\n]\nF_{ij}(t)=k_{ij}\\left[l_{ij}(t)-l_{\\text{target},ij}(t)\\right]\n(9)\nIntuitively, a larger commanded target strain magnitude results in a greater difference between the current length and the target length, thereby producing a larger internal force in the truss. To simulate the system dynamics, we integrate the force over the simulation time step\nΔ\n​\nt\n\\Delta t\nand transfer it to the connecting nodes\ni\ni\nand\nj\nj\nas a nodal impulse. Specifically, for the nodal force imposed on node\ni\ni\nfrom the truss\nE\ni\n​\nj\nE_{ij}\n:\n𝐉\nj\n→\ni\n​\n(\nt\n)\n=\nF\ni\n​\nj\n​\n(\nt\n)\n⋅\nΔ\n​\nt\n⋅\n𝐮\ni\n​\nj\n​\n(\nt\n)\n,\n\\mathbf{J}_{j\\rightarrow i}(t)=F_{ij}(t)\\cdot\\Delta t\\cdot\\mathbf{u}_{ij}(t),\n(10)\nwhere\n𝐮\ni\n​\nj\n​\n(\nt\n)\n=\n𝐱\nj\n​\n(\nt\n)\n−\n𝐱\ni\n​\n(\nt\n)\nl\ni\n​\nj\n​\n(\nt\n)\n\\mathbf{u}_{ij}(t)=\\frac{\\mathbf{x}_{j}(t)-\\mathbf{x}_{i}(t)}{l_{ij}(t)}\nis the unit directional vector pointing from node\ni\ni\nto node\nj\nj\n. We then aggregated all nodal impulses to update the nodal position. To simulate atmospheric drag and internal energy dissipation, we also apply an exponential frictional damping decay to the nodal velocities. The nodal location and velocity\n𝐯\ni\n\\mathbf{v}_{i}\nfor node\ni\ni\nis updated via symplectic Euler integration:\n𝐯\ni\n​\n(\nt\n+\nΔ\n​\nt\n)\n\\displaystyle\\mathbf{v}_{i}(t+\\Delta t)\n=\nexp\n⁡\n(\n−\nγ\n​\nΔ\n​\nt\n)\n​\n𝐯\ni\n​\n(\nt\n)\n+\n1\nm\ni\n​\n∑\nj\n∈\n𝒩\n​\n(\ni\n)\n𝐉\nj\n→\ni\n​\n(\nt\n)\n+\n𝐠\n​\nΔ\n​\nt\n,\n\\displaystyle=\\exp(-\\gamma\\Delta t)\\mathbf{v}_{i}(t)+\\frac{1}{m_{i}}\\sum_{j\\in\\mathcal{N}(i)}\\mathbf{J}_{j\\rightarrow i}(t)+\\mathbf{g}\\Delta t,\n(11)\n𝐱\ni\n​\n(\nt\n+\nΔ\n​\nt\n)\n=\n𝐱\ni\n​\n(\nt\n)\n+\n𝐯\ni\n​\n(\nt\n+\nΔ\n​\nt\n)\n​\nΔ\n​\nt\n,\n\\displaystyle\\mathbf{x}_{i}(t+\\Delta t)=\\mathbf{x}_{i}(t)+\\mathbf{v}_{i}(t+\\Delta t)\\Delta t,\nwhere\nγ\n\\gamma\nis the damping coefficient and\n𝐠\n\\mathbf{g}\nis the gravity vector (Figure\n3\nb).\nTo handle the contact with the ground, we use a high-fidelity Time of Impact (TOI) scheme to prevent interpenetration and reduce gradient discontinuity\nHu\net al.\n(\n2020\n)\n. Upon ground contact detection, the exact TOI\nτ\n∈\n[\n0\n,\nΔ\n​\nt\n]\n\\tau\\in[0,\\Delta t]\nis linearly interpolated from the pre-collision trajectory (Figure\n3\nc). When considering an infinite friction scenario, a zero-velocity boundary condition is applied at the contact point. When Coulomb friction is considered, the collision is modeled as perfectly inelastic in the normal (vertical) direction, while the tangential (horizontal) velocity is penalized by the coefficient of dynamic friction\nμ\n\\mu\n:\nv\ni\n,\ny\n+\n​\n(\nt\n)\n\\displaystyle v_{i,y}^{+}(t)\n=\n0\n\\displaystyle=0\n(12)\nv\ni\n,\nx\n+\n​\n(\nt\n)\n\\displaystyle v_{i,x}^{+}(t)\n=\n{\n0\n,\nif infinite friction\nv\ni\n,\nx\n∗\n​\n(\nt\n)\n−\nμ\n​\n|\nv\ni\n,\ny\n∗\n​\n(\nt\n)\n|\n​\nsgn\n​\n(\nv\ni\n,\nx\n∗\n​\n(\nt\n)\n)\n,\nif Coulomb\n\\displaystyle=\nwhere\n𝐯\ni\n∗\n​\n(\nt\n)\n\\mathbf{v}_{i}^{*}(t)\nand\n𝐯\ni\n+\n​\n(\nt\n)\n\\mathbf{v}_{i}^{+}(t)\ndenote the pre-collision and post-collision velocities, respectively, and\nμ\n\\mu\nis the coefficient of dynamic friction. Note that this velocity modification will be imposed before updating the nodal position in Eq.\n11\n.\nBy iteratively applying this update rule, we obtain the full motion trajectory of the robot through forward simulation (Figure\n3\n). The resulting procedure also defines a forward computational graph, which allows automatic differentiation to backpropagate the sensitivity of the nodal displacement at the final state through all integration time steps to the design variables and weights of control networks. This yields the gradients required to update the design variables and control weights.\n2.3\nDesign Optimization\nWhile the proposed framework is flexible enough to accommodate various functional objectives, we focus on forward locomotion in this study where the goal is to maximize the traveled distance. The co-design problem is formulated as a joint optimization over the structural state variables\n𝐙\n=\n{\n𝐳\ni\n​\nj\n}\n\\mathbf{Z}=\\{\\mathbf{z}_{ij}\\}\nand the neural network controller parameters\n𝜽\n\\boldsymbol{\\theta}\n. The objective is defined as the negative forward displacement of the payload head node (index\n0\n) at the final rollout timestep\nT\nT\n:\nmin\n𝐙\n,\n𝜽\n⁡\nℒ\ndisp\n​\n(\n𝐙\n,\n𝜽\n)\n=\n−\nx\n0\n​\n(\nT\n)\n\\min_{\\mathbf{Z},\\boldsymbol{\\theta}}\\;\\mathcal{L}_{\\text{disp}}(\\mathbf{Z},\\boldsymbol{\\theta})=-x_{0}(T)\n(13)\nTo obtain feasible solutions, we introduce additional constraints to the optimization problem and incorporate structural stability checks when solving the problem, as described in the following.\n2.3.1\nConstraints\nFigure 4:\nPenalty fields of (a) the global binarization constraint, (b) the pairwise orthogonal constraint, and (c) the combined penalty constraint with the optimization trajectory of design vectors throughout iterations. The three corners of each ternary plot represent discrete states, while the interior indicates intermediate interpolations between them. (d) Circled in white: an edge that struggles to decide between actuator and void, but converges towards actuator, facilitated by the iterative attraction phase. (e) Circled in yellow: zigzag design vector trajectories due to the competition between displacement and stability objectives.\nWe impose two main categories of constraints: volume fraction constraints and binarization constraints. First, we enforce volume fraction constraints on different material states. The total solid volume fraction\nV\nV\n(including both actuator and skeleton) and the actuator volume fraction\nV\nact\nV_{\\text{act}}\nare computed as\nV\n=\n1\nN\ne\n​\n∑\n(\ni\n,\nj\n)\n∈\nE\n(\np\ni\n​\nj\n,\n2\n+\np\ni\n​\nj\n,\n3\n)\n,\nV\nact\n=\n1\nN\ne\n​\n∑\n(\ni\n,\nj\n)\n∈\nE\np\ni\n​\nj\n,\n3\nV=\\frac{1}{N_{e}}\\sum_{(i,j)\\in E}(p_{ij,2}+p_{ij,3}),\\quad V_{\\text{act}}=\\frac{1}{N_{e}}\\sum_{(i,j)\\in E}p_{ij,3}\n(14)\nThese scalar volume fractions are required to satisfy the prescribed bounds\n(\nV\nmax\n,\nV\nmin\n)\n(V^{\\max},V^{\\min})\nand\n(\nV\nact\nmax\n,\nV\nact\nmin\n)\n(V_{\\text{act}}^{\\max},V_{\\text{act}}^{\\min})\n, respectively. To provide mobility for\nintermediate\nmaterial states (\nz\n~\ni\n​\nj\n,\nk\n∉\n{\n0\n,\n1\n}\n\\tilde{z}_{ij,k}\\notin\\{0,1\\}\n) that struggle to satisfy competing objectives, we progressively relax these bounds up to a small tolerance\nΔ\nV\n\\Delta_{V}\n. This way, task performance will be prioritized over a strictly satisfied volume bound, which may damage physical stability. Consequently, the effective bounds become\nV\nmax\n⁣\n∗\n=\nV\nmax\n+\nΔ\nV\nV^{\\max*}=V^{\\max}+\\Delta_{V}\n,\nV\nmin\n⁣\n∗\n=\nV\nmin\n−\nΔ\nV\nV^{\\min*}=V^{\\min}-\\Delta_{V}\n, and similarly for the actuator volume.\nSecond, we impose binarization constraints on the material state vectors to ensure they eventually achieve a fully discretized state, i.e.,\nz\n~\ni\n​\nj\n,\nk\n∈\n{\n0\n,\n1\n}\n\\tilde{z}_{ij,k}\\in\\{0,1\\}\n(Fig.\n4\n). This is accomplished through a global binarization penalty\ng\nbin\ng_{\\text{bin}}\nthat drives the\nL\n2\nL_{2}\nnorm of the material state vector toward 1\nYuhn\net al.\n(\n2023\n)\n, and a pairwise orthogonal penalty\ng\northo\ng_{\\text{ortho}}\nthat minimizes the overlap between entries corresponding to any two distinct material types:\ng\nbin\n=\n1\nN\ne\n​\n∑\n(\ni\n,\nj\n)\n∈\nE\n(\n1\n−\n∑\nk\n=\n1\n3\nz\n~\ni\n​\nj\n,\nk\n2\n)\n,\ng_{\\text{bin}}=\\frac{1}{N_{e}}\\sum_{(i,j)\\in E}\\left(1-\\sqrt{\\sum_{k=1}^{3}\\tilde{z}_{ij,k}^{2}}\\right),\n(15)\ng\northo\n=\n1\nN\ne\n​\n∑\n(\ni\n,\nj\n)\n∈\nE\n∑\nk\n≠\nl\nz\n~\ni\n​\nj\n,\nk\n​\nz\n~\ni\n​\nj\n,\nl\n0.5\n​\n(\nz\n~\ni\n​\nj\n,\nk\n+\nz\n~\ni\n​\nj\n,\nl\n)\n+\nδ\n,\ng_{\\text{ortho}}=\\frac{1}{N_{e}}\\sum_{(i,j)\\in E}\\sum_{k\\neq l}\\frac{\\tilde{z}_{ij,k}\\tilde{z}_{ij,l}}{0.5(\\tilde{z}_{ij,k}+\\tilde{z}_{ij,l})+\\delta},\n(16)\nwhere\nδ\n\\delta\nis a small value to avoid singularity. These penalty values should be controlled within a given acceptable range.\nNote that in standard density-based topology optimization, methods like Solid Isotropic Material with Penalization (SIMP) are frequently used to penalize the stiffness of intermediate probabilities, driving the optimizer toward discrete solutions\nBendsøe (\n1989\n)\n. However, due to the extreme non-convexity of the optimization landscape for discrete truss robots, such penalization can induce significant instability in the system dynamics, as observed in our preliminary tests. This motivates our use of the binarization constraints described above, which adaptively guide the solution toward discrete states over time.\n2.3.2\nOptimization Problem and Solution\nWith the above constraints, our goal is to find the optimal combination of the material design vectors\n𝐙\n=\n{\n𝐳\ni\n​\nj\n}\n\\mathbf{Z}=\\{\\mathbf{z}_{ij}\\}\nand the neural network weights\n𝜽\n\\boldsymbol{\\theta}\nthat maximizes the locomotion distance. This co-design problem can be formulated as a constrained optimization:\nmin\n𝐙\n,\n𝜽\n\\displaystyle\\min_{\\mathbf{Z},\\boldsymbol{\\theta}}\nℒ\ndisp\n​\n(\n𝐙\n,\n𝜽\n)\n\\displaystyle\\mathcal{L}_{\\text{disp}}(\\mathbf{Z},\\boldsymbol{\\theta})\n(17)\nsubject to\nV\nmin\n⁣\n∗\n≤\nV\n​\n(\n𝐙\n)\n≤\nV\nmax\n⁣\n∗\n,\n\\displaystyle V^{\\min*}\\leq V(\\mathbf{Z})\\leq V^{\\max*},\nV\nact\nmin\n⁣\n∗\n≤\nV\nact\n​\n(\n𝐙\n)\n≤\nV\nact\nmax\n⁣\n∗\n,\n\\displaystyle V_{\\text{act}}^{\\min*}\\leq V_{\\text{act}}(\\mathbf{Z})\\leq V_{\\text{act}}^{\\max*},\ng\nbin\n​\n(\n𝐙\n)\n≤\ng\nbin\n∗\n,\n\\displaystyle g_{\\text{bin}}(\\mathbf{Z})\\leq g_{\\text{bin}}^{*},\ng\northo\n​\n(\n𝐙\n)\n≤\ng\northo\n∗\n,\n\\displaystyle g_{\\text{ortho}}(\\mathbf{Z})\\leq g_{\\text{ortho}}^{*},\nwhere\ng\nbin\n∗\ng_{\\text{bin}}^{*}\nand\ng\northo\n∗\ng_{\\text{ortho}}^{*}\nrepresent the acceptable threshold for the binarization and pairwise orthogonal constraints, respectively.\nWe solve this constrained problem via iterative gradient-based optimization. To promote the initial exploration of vast design possibilities, binarization constraints are enforced through the Augmented Lagrangian (AL) method\nYuhn\net al.\n(\n2023\n); Fortin and Glowinski (\n2000\n)\n. Unlike volume fraction constraints, which are strictly enforced at all times, binarization constraints are allowed to be occasionally violated to increase the exploration of discrete choices and open up potential pathways to better solutions. The AL method provides a rigorous mechanism to adaptively adjust the penalization strength to achieve this. Empirically, we find this approach yields better performance compared with strictly enforcing the constraints. The objective function with AL constraints is defined as:\nℒ\n​\n(\n𝐙\n,\n𝝀\n,\n𝝉\n)\n=\nℒ\ndisp\n+\n∑\nk\n=\n1\n4\n(\n−\nλ\nk\n​\nv\nk\n+\n1\n2\n​\nτ\nk\n​\nv\nk\n2\n)\n,\n\\mathcal{L}(\\mathbf{Z},\\boldsymbol{\\lambda},\\boldsymbol{\\tau})=\\mathcal{L}_{\\text{disp}}+\\sum_{k=1}^{4}\\left(-\\lambda_{k}v_{k}+\\frac{1}{2}\\tau_{k}v_{k}^{2}\\right),\n(18)\nwhere\nv\nk\nv_{k}\ndenotes the violation magnitude of the\nk\nk\n-th binarization constraint (one global\nL\n2\nL_{2}\npenalty and three pairwise orthogonal penalties). The Lagrangian multipliers\n𝝀\n\\boldsymbol{\\lambda}\nare updated dynamically at each iteration according to\nλ\nk\n←\nλ\nk\n−\nτ\nk\n​\nv\nk\n\\lambda_{k}\\leftarrow\\lambda_{k}-\\tau_{k}v_{k}\n. To prevent over-penalization, the penalty weight\nτ\nk\n\\tau_{k}\nis increased by a factor of\na\na\nif the constraint violation\nv\nk\nv_{k}\nincreases between iterations, and decreased by\n1\n/\na\n1/a\nif the violation decreases.\nAll material design vectors\n𝐙\n\\mathbf{Z}\nare initialized uniformly and updated iteratively via the Method of Moving Asymptotes (MMA). The MMA optimizer takes in the augmented objective\nℒ\n​\n(\n𝐙\n,\n𝝀\n,\n𝝉\n)\n\\mathcal{L}(\\mathbf{Z},\\boldsymbol{\\lambda},\\boldsymbol{\\tau})\n, the volume fraction constraints, and gradients from the differentiable simulation. The MLP controller weights\n𝜽\n\\boldsymbol{\\theta}\nare initialized using Xavier Initialization and updated using the Adam optimizer, which represents the state-of-the-art for gradient-based optimization over large parameter sets in neural networks. Material design vectors and MLP weights are updated alternately at a 3:2 ratio, based on our preliminary experiments, to enable a balanced update between robot morphology and control, supporting optimal co-evolution of the configuration.\nDespite the binarization constraint penalization, in practice, some edges can still become trapped in intermediate material states in the optimization (Fig.\n4\ne). In these cases, the dynamic system relies on a delicate structural integrity and balance that is maintained by these physically infeasible intermediate materials. Once these materials are removed, the delicate balance may be disrupted, potentially causing collapse of the structure or disjoint geometry, which can drastically alter the system dynamics. Consequently, performance losses evaluated on intermediate designs rarely reflect the true performance of the final discrete robot.\nTo reliably probe the structural integrity of the final discrete robot, we propose to implement an auxiliary stability evaluation along with the ordinary objective function evaluation. This pass implements a globally centered softmax function to project the continuous design variables\n𝐳\n\\mathbf{z}\ninto a highly sharpened proxy geometry\n𝐳\n∗\n\\mathbf{z}^{*}\nusing a scaling factor\nβ\nstab\n\\beta_{\\text{stab}}\nmuch higher than the\nβ\n\\beta\nwe use in Eq.\n1\n:\nz\n¯\nk\n=\n1\nN\ne\n​\n∑\n(\ni\n,\nj\n)\n∈\nE\nz\ni\n​\nj\n,\nk\n\\bar{z}_{k}=\\frac{1}{N_{e}}\\sum_{(i,j)\\in E}z_{ij,k}\n(19)\nz\ni\n​\nj\n,\nk\n∗\n=\nexp\n⁡\n(\nβ\nstab\n​\n(\nz\ni\n​\nj\n,\nk\n−\nz\n¯\nk\n)\n)\n∑\nl\n=\n1\n3\nexp\n⁡\n(\nβ\nstab\n​\n(\nz\ni\n​\nj\n,\nl\n−\nz\n¯\nl\n)\n)\nz_{ij,k}^{*}=\\frac{\\exp(\\beta_{\\text{stab}}(z_{ij,k}-\\bar{z}_{k}))}{\\sum_{l=1}^{3}\\exp(\\beta_{\\text{stab}}(z_{ij,l}-\\bar{z}_{l}))}\n(20)\nThis globally centered projection serves as a high-fidelity proxy of the final discrete geometry, operating on the assumption that design vectors will linearly diverge from the global mean under continuous binarization pressure. The moving displacement of this proxy design is evaluated and used as an auxiliary objective function\nℒ\nstab\n=\n−\nx\n0\n​\n(\nT\n)\n\\mathcal{L}_{\\text{stab}}=-x_{0}(T)\n, which we term a\nstability pass\n, in contrast to the ordinary objective evaluation with\nβ\n\\beta\n, referred to as a\nperformance pass\n. During optimization, stability passes are interleaved with performance passes, and the resulting design variable updates are blended according to a predefined ratio. However, the aggressive sharpening induced by\nβ\nstab\n\\beta_{\\text{stab}}\ncan lead to severe vanishing gradients. To mitigate this, we adopt a Straight-Through Estimator (STE) to compute the gradient in a more reliable way\nBengio\net al.\n(\n2013\n)\n.\nFigure 5:\nOptimization history of the co-design process corresponding to the design in Figure.\n6\nb. (a–d) Intermediate designs at iterations 20, 70, 110, and 200, respectively, showing the evolution of the structure. (d) Structural fine-tuning during the design vector attraction stage. (e) Fully binarized and frozen structural layout in the control-only design stage, where only the MLP controller weights are fine-tuned.\nTo accelerate convergence during the later stages of optimization, where the continuous material design vectors\n𝐳\ni\n​\nj\n\\mathbf{z}_{ij}\nexhibit reduced mobility due to smaller gradients (Fig.\n4\nd), we implement a iterative vector attraction phase (Fig.\n5\n). If the maximum value of a material state vector\nz\n~\ni\n​\nj\n\\tilde{z}_{ij}\nexceeds a confidence threshold\nτ\n\\tau\n, we deem the largest entry as the dominant state. The design vector is progressively pulled toward its dominant discrete material state using an additive nudge\nγ\n\\gamma\n:\nz\ni\n​\nj\n,\nc\n∗\n←\nz\ni\n​\nj\n,\nc\n∗\n+\nγ\n,\nz\ni\n​\nj\n,\nk\n←\nz\ni\n​\nj\n,\nk\n−\nγ\nN\n−\n1\n​\nfor\n​\nk\n≠\nc\n∗\n,\nz_{ij,c^{*}}\\leftarrow z_{ij,c^{*}}+\\gamma,\\quad z_{ij,k}\\leftarrow z_{ij,k}-\\frac{\\gamma}{N-1}\\text{ for }k\\neq c^{*},\n(21)\nwhere\nc\n∗\nc^{*}\nis the index of the dominant material state.\nBoth the confidence threshold\nτ\n\\tau\nand the nudge strength\nγ\n\\gamma\nare linearly annealed over time. A hard discretization snap is enforced toward the end of the optimization process, after which the strictly binarized topology and material layout are frozen, and the neural controller parameters\n𝜽\n\\boldsymbol{\\theta}\nare fine-tuned alone for the remaining iterations (Fig.\n5\n).\nAlgorithm 1\nMulti-Stage Co-Design Optimization\n1:\nInput:\nInitial design vectors\n𝐙\n∈\nℝ\nN\ne\n×\n3\n\\mathbf{Z}\\in\\mathbb{R}^{N_{e}\\times 3}\n, MLP\n𝜽\n\\boldsymbol{\\theta}\n, Hyper-parameters.\n2:\nOutput:\nDiscrete design\n𝐙\n∗\n\\mathbf{Z}^{*}\n, fine-tuned controller\n𝜽\n∗\n\\boldsymbol{\\theta}^{*}\n.\n3:\nInit. multipliers\n𝝀\n←\n𝟎\n\\boldsymbol{\\lambda}\\leftarrow\\mathbf{0}\n, penalties\n𝝉\n←\nτ\n0\n\\boldsymbol{\\tau}\\leftarrow\\tau_{0}\n.\n4:\nfor\nI\n​\nt\n​\ne\n​\nr\n=\n1\nIter=1\nto\n300\n300\ndo\n5:\nInterpolate\nT\ngrad\nT_{\\text{grad}}\nand volume tolerance\nΔ\nV\n\\Delta_{V}\n.\n6:\nAlternate passes\n∈\n{\nController, Performance, Stability\n}\n\\in\\{\\textit{Controller, Performance, Stability}\\}\n.\n7:\nif\nI\n​\nt\n​\ne\n​\nr\n<\n240\nIter<240\nthen\n⊳\n\\triangleright\nPhase: Co-design\n8:\nProject\n𝐙\n→\n𝐙\n~\n\\mathbf{Z}\\to\\mathbf{\\tilde{Z}}\nvia softmax\nβ\n\\beta\n(Eq.\n1\n).\n9:\nSimulate dynamics for\nT\nT\nsteps (Eq.\n8\n–\n12\n).\n10:\nCompute\nℒ\ndisp\n=\n−\nx\n0\n​\n(\nT\n)\n\\mathcal{L}_{\\text{disp}}=-x_{0}(T)\nand constraints\nv\nk\nv_{k}\n.\n11:\nif\nController\npass\nthen\n12:\nUpdate\n𝜽\n\\boldsymbol{\\theta}\nvia Adam w.r.t.\nℒ\ndisp\n\\mathcal{L}_{\\text{disp}}\n.\n13:\nelse\nif\nPerformance\npass\nthen\n14:\nUpdate\n𝐙\n\\mathbf{Z}\nvia MMA w.r.t. AL obj. (Eq.\n17\n).\n15:\nelse\nif\nStability\npass\nthen\n16:\nProject proxy\n𝐙\n∗\n\\mathbf{Z}^{*}\nvia centered softmax\nβ\nstab\n\\beta_{\\text{stab}}\n.\n17:\nCompute\nℒ\nstab\n\\mathcal{L}_{\\text{stab}}\n& update\n𝐙\n\\mathbf{Z}\nvia STE + MMA.\n18:\nend\nif\n19:\nUpdate AL params\n𝝀\n,\n𝝉\n\\boldsymbol{\\lambda},\\boldsymbol{\\tau}\nusing violations\nv\nk\nv_{k}\n.\n20:\nif\nI\n​\nt\n​\ne\n​\nr\n≥\n170\nIter\\geq 170\nthen\n⊳\n\\triangleright\nPhase: Iterative Attraction\n21:\nApply iterative attraction(Eq.\n21\n).\n22:\nend\nif\n23:\nelse\nif\nI\nt\ne\nr\n=\n=\n240\nIter==240\nthen\n⊳\n\\triangleright\nPhase: Fine-tune\n24:\nSnap\n𝐙\n\\mathbf{Z}\nto\n{\n0\n,\n1\n}\n3\n\\{0,1\\}^{3}\none-hot encodings.\n25:\nFreeze layout:\n𝐙\n∗\n←\n𝐙\n\\mathbf{Z}^{*}\\leftarrow\\mathbf{Z}\n.\n26:\nelse\n27:\nSimulate dynamics using frozen geometry\n𝐙\n∗\n\\mathbf{Z}^{*}\n.\n28:\nUpdate only\n𝜽\n\\boldsymbol{\\theta}\nvia Adam w.r.t.\nℒ\ndisp\n\\mathcal{L}_{\\text{disp}}\n.\n29:\nend\nif\n30:\nend\nfor\n31:\nreturn\n𝐙\n∗\n,\n𝜽\n∗\n\\mathbf{Z}^{*},\\boldsymbol{\\theta}^{*}\n2.3.3\nImplementation Details\nThe following hyperparameters are chosen based on preliminary experiments. In this study, the physical simulation is evaluated for up to 300 design iterations. Each rollout integrates 8192 timesteps of\nΔ\n​\nt\n=\n0.002\n\\Delta t=0.002\ns using a symplectic first-order Euler method in a differentiable simulation platform, Taichi, as described in Section 2.2. To preserve dynamic fidelity while accelerating convergence, gradients are initially calculated for only 2048 timesteps, and are gradually extended to a maximum of 4096 timesteps between iterations 80 and 150. The volume bound tolerance\nΔ\nV\n\\Delta_{V}\nis linearly widened from zero to\n0.03\n0.03\nbetween iterations 110 and 150. Iterative vector attraction begins at iteration 170, followed by a hard discretization snap at iteration 240. The neural controller is then fine-tuned on the strictly binarized topology for the remaining iterations (240–300). The complete pseudo-code implementation is shown in Algorithm\n1\n.\nWe select\nN\nCPG\n=\n10\nN_{\\text{CPG}}=10\nCPG signals and a fundamental frequency of\nω\n=\n10\n\\omega=10\nfollowing\nHu\net al.\n(\n2020\n)\n. Furthermore, we found that utilizing more than 10 CPG signals tends to desynchronize the robot’s movement and harm overall locomotion stability. Similarly, to ensure the controller remains lightweight and stable during the highly non-convex co-design process, we adopt a hidden layer dimension of 32. The final MLP has layer widths of\n(\nN\nC\n​\nP\n​\nG\n+\n4\n​\nN\nm\n+\n2\n,\nD\nh\n​\ni\n​\nd\n​\nd\n​\ne\n​\nn\n,\nN\ne\n)\n=\n(\n156\n,\n32\n,\n110\n)\n(N_{CPG}+4N_{m}+2,D_{hidden},N_{e})=(156,32,110)\n.\nThe specific material properties assigned to the void, skeleton, and actuator states are summarized in Table\n1\n. Hyperparameters for the constraints, Augmented Lagrangian penalties, and optimization solver are listed in Table\n2\n.\nTable 1:\nMaterial properties assigned to the three discrete states.\nMaterial State\nk\n(N/m)\nρ\n\\rho\n(g/m)\na\nmax\na_{\\max}\nVoid (\nV\nV\n)\n1\n×\n10\n−\n7\n1\\times 10^{-7}\n1\n×\n10\n−\n5\n1\\times 10^{-5}\n0.0\n0.0\nSkeleton (\nS\nS\n)\n4\n×\n10\n2\n4\\times 10^{2}\n30.0\n30.0\n0.0\n0.0\nActuator (\nA\nA\n)\n3\n×\n10\n1\n3\\times 10^{1}\n100.0\n100.0\n0.35\n0.35\nTable 2:\nHyperparameters for simulation and optimization.\nParameter\nSymbol\nValue\nIntegration time step\nΔ\n​\nt\n\\Delta t\n0.002\n0.002\ns\nTotal rollout steps\nT\nT\n8192\n8192\nMax topology volume fraction\nV\nmax\nV^{\\max}\n0.50\n0.50\nMin topology volume fraction\nV\nmin\nV^{\\min}\n0.50\n0.50\nMin actuator volume fraction\nV\nact\nmin\nV_{\\text{act}}^{\\min}\n0.20\n0.20\nMax actuator volume fraction\nV\nact\nmax\nV_{\\text{act}}^{\\max}\n0.22\n0.22\nAL initial penalty weight\nτ\n0\n\\tau_{0}\n0.3\n0.3\nAL penalty annealing factor\na\na\n1.01\n1.01\nPerformance pass inverse temp.\nβ\n\\beta\n20.0\n20.0\nStability pass inverse temp.\nβ\nstab\n\\beta_{\\text{stab}}\n500.0\n500.0\nSTE inverse temp.\nβ\nSTE\n\\beta_{\\text{STE}}\n20.0\n20.0\n3\nResults and Discussion\n3.1\nEffect of Design Initialization\nFigure 6:\nThe baseline and optimization results with varying initial designs. (a) Vertical actuation layout baseline without optimization. (b)-(d) Optimization results from different initial heuristics: (b) Stability heuristic : top springs receive a higher void ratio. (c) Three-legged heuristic: shaded region receives a higher void ratio. (d) No heuristics. The target position is marked by a vertical dashed line. Payload node’s trajectories and final horizontal displacements of the robot are plotted in green, while instantaneous actuator strains are visualized with red denoting extension and blue denoting contraction.\nWe first investigate whether the proposed platform can effectively navigate the mixed-variable design space to discover optimal configurations of topology, material layout, and control. Furthermore, we verify whether co-design yields improved dynamic performance by comparing our method against a baseline that designs configuration and control separately, under identical volume fraction constraints.\nWe adapt the baseline design (Figure\n6\na) from\nHu\net al.\n(\n2020\n)\n, which features a three-legged topology with vertically actuated active trusses and passive cross-braces to resist gravity. This configuration follows standard heuristics for walking robots, with three limbs to support an alternating gait. Additionally, it serves as the sequential design baseline where the pre-designed structural and material distributions are first fixed, then followed by the optimization of the neural network controller with Xavier-initialized weights. To provide a non-zero initial gradient, the payload node (bottom-left) is offset to\nx\n=\n0.1\nx=0.1\nm for all robots. The target positional vector is set to\n(\n2\n,\n0.1\n)\n(2,0.1)\nm.\nThe baseline robot learns an optimal control policy for its fixed material layout over 200 iterations, achieving a final horizontal displacement of 1.14 m. However, the prevalent passive cross-bracing restricted the stroke magnitude of its limbs, causing inconsistent ground contact dynamics that destabilize its gait during later stages of the rollout, as indicated by the increasing disorderness in the payload trajectory.\nNext, we compare the baseline to Design\n6\nb, which is fully co-designed using the proposed framework. To ensure a fair comparison, we constrained both robots to the same total topology and actuation volume budgets. Design\n6\nb is initialized using a gentle stability heuristic: trusses are assigned an initial ratio bias toward the void state proportional to their vertical elevation (y-height), with the topmost truss receiving a maximum ratio shift of\nΔ\n​\nz\n~\ni\n​\nj\n,\n0\n=\n+\n12\n%\n\\Delta\\tilde{z}_{ij,0}=+12\\%\n. The stability heuristic is aimed at preventing structural collapse, commonly caused by sparse, top-heavy geometries or large, unsupported active clusters. By promoting dense, low center of mass structures, this heuristic narrows the design space to favor solutions better suited for dynamic stability. The optimization trajectory of each edge design vector is visualized in Figure\n4\n, and the corresponding structural evolution of the entire robot is shown in Figure\n5\n. Upon initialization, all truss design vectors lie in intermediate states. As the optimization proceeds, most design vectors migrate rapidly and smoothly toward discrete states within 150 iterations under the Augmented Lagrangian binarization penalty (Figures\n4\nc). Volume fraction constraints encourage the solver to better allocate actuators and structural elements, leading to a significant decrease in the objective function and a corresponding improvement in the walking distance (Figure\n5\na–c). Meanwhile, some trusses struggle to converge to a single material state (Figures\n4\nd and\n5\nc). These intermediate trusses are addressed in a second stage, where we introduce the progressive nudge of the iterative attraction phase to achieve binarization (Figure\n5\nd). During this process, those trusses gradually resolve the competition between performance and stability objectives, indicative in their zigzagging trajectories (Figure\n4\ne). Ultimately, the design achieves full convergence before the hard binarization snap (Figure\n5\ne), with additional iterations devoted to further control optimization. The final converged morphology for Design\n6\nb adopts a propulsive leaping gait, relying primarily on a massive back leg for thrust while utilizing a smaller front leg for traction. This co-designed robot achieves a final displacement of 1.90 m, outperforming the sequential baseline by 66%.\nHowever, the notable performance improvement demonstrated by\n6\nb could be simply attributed to a superior initial heuristic compared with the baseline. To test this possibility, we introduce a different initial solution in Design\n6\nc that mirrors the three-legged configuration of the baseline, allowing us to examine whether co-design can consistently improve locomotion performance across alternative initializations. Here, trusses that are void in the baseline (Design\n6\na) are initialized with a strong bias toward the void state, while all remaining active and skeletal trusses start with completely uniform and equal ratios for each state. During optimization, Design\n6\nc concentrates its actuators within the middle leg (Figure\n6\nc). This allocation overcomes the restricted stroke observed in the baseline, enabling sweeping motions and lengthened strides to achieve a final displacement of 1.87 m. This result falls slightly short of Design\n6\nb, indicating that the performance indeed depends on initialization, as expected for such a nonconvex optimization problem. However, it still substantially outperforms the baseline that shares the same three-legged initial configuration. This result highlights the advantage of co-design over separated design.\nFinally, we verify that even for the most challenging scenario, a heuristics-free initialization (Figure\n6\nd), the proposed platform can still find a viable solution. Here, optimization begins with completely uniform material ratios for the void, skeleton, and actuator states across all trusses. The algorithm receives no initial guidance and is forced to search for a structurally valid and dynamically favorable solution from an unrestricted design space. Despite this lack of guidance, the co-design platform is still able to discover a viable design that achieves a travel distance of 0.98m. The resulting Design\n6\nd adopts a hopping gait: using its front leg as support and frugally allocating the highly compliant muscle near the back leg payload for motion. Although the heuristic-free optimization succeeds in finding a valid locomotion strategy, it still underperforms relative to Designs\n6\nb and\n6\nc, as we intend to choose a challenging initial solution to test optimization sensitivity. Future gradient-based co-design approaches could be combined with global search methods, such as genetic algorithms, to seed the solver with strong initial solutions. Interestingly, Design\n6\nd automatically discovered structural features similar to the stability-heuristics Design\n6\nb despite receiving no guidance. Common emergent features include disconnecting specific bottom trusses for larger strides, and concentrating topology to the lower half for a low center of gravity.\n3.2\nIndividual and Collective Contribution of Design Entities\nFigure 7:\nCombinatorial ablation study results. Robots are optimized from an identical initialization. A\ncross mark\nindicates a disabled design entity, while a\ntick mark\nindicates indicates an enabled entity.\nFigure 8:\nQuatitative ablation results. Grouped by design entities, the average with and without performance for each entity is compared. Actuation layout has the largest contribution to improved performance, while control pattern has the smallest.\nWe continue to leverage our platform to investigate the individual and collective contributions of design entities to locomotive performance. We conduct ablation studies by selectively disabling specific entities, allowing us to isolate their individual effects or examine pairwise combinations. We then compare these ablated trials with the fully co-designed case to quantify the benefits of jointly optimizing all three design entities.\nBy combinatorially considering the enabled/disabled design of the three design entities, we obtain eight possible design schemes or trials (Figure\n7\n). Specifically, trials with the control design disabled (Designs\n7\na, c, e, and g) operate using frozen MLP weights from Xavier Initialization. For no-topology-design trials (Designs\n7\na, b, e, and f), a default fully-filled topology is used, while a uniform distribution of vertical actuators as used the default actuation layout for no-material-design trials (Designs\n7\na, b, c, and d). The same initialization in Figure\n6\nb is applied to all trials that enable topology design (Designs\n7\nc, d, g, and h). To ensure the topology remains frozen while materials can still be redistributed, Trials\n7\ne and f are subject to a topology volume fraction of\nV\nmin\n=\n0.90\nV^{\\min}=0.90\n, which is only appropriately strict to prevent sharp design vector motions at the simplex edges (as seen in Figure\n4\nc). Conversely, to freeze the material layout while permitting topological changes in Trials\n7\nc and d, we subtract a small constant from the non-dominant solid entries of the design vector before every softmax projection, whereas the void entries are left unaltered to enable topological design.\nThe quantitative results are summarized in Figure\n8\n. Actuation layout demonstrates the largest individual contribution to performance improvement, increasing the average displacement by 781% compared to the \"without\" conditions (Figure\n8\nb). Admittedly, the default actuator distribution imposes stringent requirements on compatible topologies, which must mechanically facilitate high-stroke motions for traversal. Yet, actively co-designing the actuation layout consistently yields substantial performance improvements regardless of the underlying topology (comparing Trials\n7\na–d to\n7\ne–h), highlighting its high adaptability to varied initial conditions and its values in robotic design. Topological design produces an improvement of 116% (Figure\n8\na), while weak on its own, it is a powerful multiplier for the positive impact of material design. By comparing trials optimized with and without topology while holding the other two design entities constant (Trial\n7\ne vs. g, and\n7\nf vs. h), we observe that topological optimization consistently increases traversal distance, even on top of the already substantial gains achieved by actuation design alone.\nSurprisingly, control pattern design demonstrates a small individual contribution and occasionally impacts performance negatively (Trial\n7\nc vs. d). This behavior likely occurs because the topology and material distribution themselves are suboptimal and provide limited mobility, leaving little room for further improvement through control optimization alone. The degradation may also arise because the severe non-linearities introduced by ground contacts pollute the gradient propagation through time; when coupled with a sub-optimal physical structure, the resulting small loss, and consequently small gradient amplitude, muddies the directional information provided to the Adam optimizer. However, when combined with material layout optimization, control consistently enhances traversal, as observed in Trials\n7\ne vs. f and\n7\ng vs. h. Most notably, when we further incorporate the topology entity, co-evolving control alongside all other entities, travel distance increases by 87% compared to the trial without control optimization (from 1.02 m in Trial\n7\ng to 1.91 m in Trial\n7\nh). This result demonstrates that the benefits of jointly optimizing topology, material distribution, and control exceed those achievable by optimizing the entities in isolation.\nAdditionally, we observe that in trials producing substantial displacement (Designs\n7\ne–h), the resultant material distributions and locomotion strategies are topology-dependent. For example, the fully-filled topologies in Trials\n7\ne and f both allocate actuators heavily to the right and bottom edges of the robot to maximize traction. Conversely, the freely evolved topologies in Trials\n7\ng and h allocate actuators to both the rear and front legs while independently discovering an identical central motif: inserting a horizontal actuator directly between passive cross-braces for enhanced coordination between the front and rear legs. This phenomenon mirrors convergent evolution in nature, where identical musculoskeletal motifs emerge across species with similar body plans. This further highlights the importance of simultaneously optimizing all design entities. Discovering a highly optimized topology without its uniquely compatible actuation layout (Trial\n7\nd vs. h), or vice versa (Trial\n7\nf vs. h), leads to substantially weaker performance. This outcome indicates a strong coupling between material and topology, emphasizing that the two must be jointly designed to enable optimal performance.\n3.3\nGenerality to Other Tasks and Environments\nFigure 9:\nAlternative tasks and environments: (a) upward incline; (b)\n5\n×\n5\n5\\times 5\nnodes design space; and (c) slippery ground contact.\nFinally, we apply the proposed co-design framework to several additional cases with varying optimization objectives, design space, and environmental parameters to demonstrate its flexibility. All cases begin with the stability heuristics described in Section\n3.1\n.\nIn design\n9\na, we place the locomotion goal on top of a 15-degree incline. Although sharing the same initialization as Design\n6\nb, the final robot morphology changed in adapting to this new target function. Compared to Design\n6\nb, the final design\n9\na evolved to an even slimmer structure to further prioritize a low center of mass, crucial for stabilizing against the toppling forces of the inclined ground boundary. Dynamically, it adopts an arching motion to gain altitude as well as forward distance, that is a combination of hopping (Design\n6\nc) and crawling (Design\n6\nd). Additionally, it slightly undercuts the lower volume bound for topology and actuation in exchange for having to carry less weight upwards, achieving a horizontal distance of 1.36 m and vertical elevation of 0.35 m.\nFor Design\n9\nb, we perform optimization on a smaller design space of\n5\n×\n5\n5\\times 5\nnodal grid, rather than a\n6\n×\n6\n6\\times 6\nnodal grid in all other cases. This reduction in available material resources makes the allocation of materials and topology more critical. Our co-design platform reliably generalizes to this design space and automatically rediscovered the leg division strategy observed in designs Design\n6\nb and d, where the bottom trusses are broken to form a rear and front leg. It used a front-leg assisted leaping gait, primarily relied upon the rear actuators, and achieved a traversal distance of 1.10 m upon final evaluation, comparable to that of Design\n6\nd.\nOur proposed framework is also flexible enough to handle varying physical and environmental parameters. To demonstrate this capability, we apply it to a locomotion design problem under different ground friction conditions, which strongly influence contact mechanics and locomotion dynamics. Specifically, Design\n9\nc adopts the Coulomb friction contact model specified in Section\n2.2\n, differentiating itself from the infinite friction model used in all other designs. The coefficient of dynamic friction is chosen as\nμ\n=\n2.5\n\\mu=2.5\nRoth\net al.\n(\n1943\n)\n. Under this setting, it exhibits a consistent morphological adaptation to the new physical environment, adopting a locomotion strategy unobserved in previous designs. Instead of dynamically lifting the payload and repositioning it forward with every gait, as observed in Designs\n7\ng and h with similar topology, it keeps the heavy payload with the ground to provide anchorage against skidding. Interestingly, during the first 0.5 meters, the robot folds its front leg inward, increasing the contact area and effectively using it as a friction pad. This behavior represents a beneficial morphological transformation that leverages the coupled effects of environmental physics, topology, material layout, and actuation control.\n4\nConclusion\nIn this work, we have developed a co-design framework to automatically identify the optimal combination of topological layout, distribution of passive and active materials, and control policy of a discrete truss-lattice robot, maximizing its performance across a range of dynamic locomotive tasks. Within this framework, we construct a unified design representation that links mixed variable structural and material design with a spatiotemporal neural network controller. This formulation allows different design entities to be coupled within a differentiable physics simulator that efficiently evaluates system dynamics and provides gradient information, even under frictional contacts and varying environments. Unlike most existing methods that treat these design entities separately, our approach optimizes them jointly within a constrained optimization framework that accounts for structural stability and physical feasibility, providing greater flexibility to achieve improved performance.\nThrough a variety of design cases, we demonstrate that the proposed framework reliably discovers high-performance solutions even without heuristic guidance. With only simple initialization, it can outperform carefully crafted baseline designs developed through sequential design processes. Across tasks, the framework identifies diverse material allocations and locomotion strategies for the same traversal objective, such as leaping, sweeping, and hopping gaits, indicating that co-design expands the accessible morphological design space and enables not only higher performance solutions but also a broader range of viable designs. The framework also adapts to different design requirements and environmental conditions, automatically generating robots whose structures, material distributions, and control policies are tailored to specific tasks to produce effective motion patterns. These results highlight both the adaptability of the proposed method and the importance of co-design for enabling niche robotic systems that accommodate the specific requirements of customized applications.\nFurther, this study uncovers the contributions of structural, material, and control design entities in robotic locomotion. We found that material layout plays the most critical role, as redistributing actuation within a given configuration can effectively reshape robot dynamics and achieve strong performance even when the structure and control are suboptimal. In contrast, control alone cannot compensate for limitations in structure or actuation and is largely bounded by the underlying structural and material design. More importantly, the interaction among structure, materials, and control produces performance gains that exceed the contributions of any single component. We also observe convergent structural motifs emerging across designs with similar objectives, suggesting an underlying form-function relationship that arises from the synergy among these design entities. These insights further highlight the importance and value of simultaneous co-design realized in the proposed framework.\nThere are several limitations in this work that motivate future research. First, as expected for highly nonconvex optimization problems, the final performance remains sensitive to initialization. A promising direction is to combine the proposed gradient-based search with global optimization methods, such as evolutionary algorithms\nGu\net al.\n(\n2025\n); Strgar and Kriegman (\n2025\n)\n, to improve exploration. Second, as an exploratory study, we employ a simplified simulator. Although the corresponding physical system has recently been realized with good agreement to simulation\nStrgar\net al.\n(\n2024\n)\n, incorporating richer physical effects such as bending and material nonlinearities would further improve fidelity. In addition, while we currently optimize the neural controller using gradient-based methods, integrating reinforcement learning strategies may provide greater generalization. Finally, accounting for manufacturing variability and environmental uncertainty will be important for enabling more robust robotic designs.\nWe envision that the proposed framework can be broadly adopted to establish design principles and develop computational tools for a wide range of robotic systems. By customizing each component, the approach is generalizable and applicable to diverse materials and stimuli. We anticipate that it will accelerate the development of robotic material systems with various applications, including bio-hybrid robots\nKinjo\net al.\n(\n2024\n); Sun\net al.\n(\n2020\n)\n, mechanical computing systems\nLiang\net al.\n(\n2024\n); Lee\net al.\n(\n2022\n)\n, and more.\nAcknowledgments\nWe acknowledge support from the Department of Mechanical Engineering at Carnegie Mellon University.\nReferences\n[1]\nJ. Aguilar, T. Zhang, F. Qian, M. Kingsbury, B. McInroe, N. Mazouchova, C. Li, R. Maladen, C. Gong, M. Travers, R. L. Hatton, H. Choset, P. B. Umbanhowar, and D. I. Goldman\n(2016-09)\nA review on locomotion robophysics: the study of movement at the intersection of robotics, soft matter and dynamical systems\n.\nReports on Progress in Physics\n79\n(\n11\n),\npp. 110001\n.\nExternal Links:\nDocument\n,\nLink\nCited by:\n§1\n.\n[2]\nC. Armanini, F. Boyer, A. T. Mathew, C. Duriez, and F. Renda\n(2023)\nSoft robots modeling: a structured overview\n.\nIEEE Transactions on Robotics\n39\n(\n3\n),\npp. 1728–1748\n.\nExternal Links:\nDocument\nCited by:\n§1\n.\n[3]\nR. Baines, F. Fish, J. Bongard, and R. Kramer-Bottiglio\n(2024-11)\nRobots that evolve on demand\n.\nNature Reviews Materials\n9\n(\n11\n),\npp. 822–835\n(\nen\n).\nExternal Links:\nISSN 2058-8437\n,\nLink\n,\nDocument\nCited by:\n§1\n.\n[4]\nM. P. Bendsøe\n(1989-12)\nOptimal shape design as a material distribution problem\n.\nStructural optimization\n1\n(\n4\n),\npp. 193–202\n(\nen\n).\nExternal Links:\nISSN 1615-1488\n,\nLink\n,\nDocument\nCited by:\n§2.3.1\n.\n[5]\nY. Bengio, N. Léonard, and A. Courville\n(2013)\nEstimating or propagating gradients through stochastic neurons for conditional computation\n.\narXiv preprint arXiv:1308.3432\n.\nCited by:\n§2.3.2\n.\n[6]\nR. C. Bertossa\n(2011-07)\nMorphology and behaviour: functional links in development and evolution\n.\nPhilosophical Transactions of the Royal Society B: Biological Sciences\n366\n(\n1574\n),\npp. 2056–2068\n.\nExternal Links:\nISSN 0962-8436\n,\nLink\n,\nDocument\nCited by:\n§1\n.\n[7]\nA. Bhattacharyya, J. Kim, L. R. Alacoque, and K. A. James\n(2023-12)\nDesign Synthesis of a 4D-Printed Self-Tying Knot With Programmable Morphology\n.\nJournal of Mechanical Design\n146\n(\n063303\n).\nExternal Links:\nISSN 1050-0472\n,\nLink\n,\nDocument\nCited by:\n§1\n,\n§1\n.\n[8]\nG. Bordiga, E. Medina, S. Jafarzadeh, C. Bösch, R. P. Adams, V. Tournat, and K. Bertoldi\n(2024-11)\nAutomated discovery of reprogrammable nonlinear dynamic metamaterials\n.\nNature Materials\n23\n(\n11\n),\npp. 1486–1494\n(\nen\n).\nExternal Links:\nISSN 1476-4660\n,\nLink\n,\nDocument\nCited by:\n§1\n.\n[9]\nK. Caluwaerts, J. Despraz, A. Işçen, A. P. Sabelhaus, J. Bruce, B. Schrauwen, and V. SunSpiral\n(2014)\nDesign and control of compliant tensegrity robots through simulation and hardware validation\n.\nJournal of the royal society interface\n11\n(\n98\n).\nCited by:\n§1\n.\n[10]\nJ. Davy, P. Lloyd, J. H. Chandler, and P. Valdastri\n(2023)\nA framework for simulation of magnetic soft robots using the material point method\n.\nIEEE Robotics and Automation Letters\n8\n(\n6\n),\npp. 3470–3477\n.\nExternal Links:\nDocument\nCited by:\n§1\n.\n[11]\nT. Dinev, C. Mastalli, V. Ivan, S. Tonneau, and S. Vijayakumar\n(2022)\nA versatile co-design approach for dynamic legged robots\n.\nIn\n2022 IEEE/RSJ International Conference on Intelligent Robots and Systems (IROS)\n,\npp. 5562–5569\n.\nCited by:\n§1\n.\n[12]\nT. Du, K. Wu, P. Ma, S. Wah, A. Spielberg, D. Rus, and W. Matusik\n(2021-11)\nDiffPD: differentiable projective dynamics\n.\nACM Trans. Graph.\n41\n(\n2\n).\nExternal Links:\nISSN 0730-0301\n,\nLink\n,\nDocument\nCited by:\n§1\n.\n[13]\nM. Fortin and R. Glowinski\n(2000)\nAugmented lagrangian methods: applications to the numerical solution of boundary-value problems\n.\nVol.\n15\n,\nElsevier\n.\nCited by:\n§2.3.2\n.\n[14]\nK. Fu, D. Moreno, M. Yang, and K. L. Wood\n(2014-10)\nBio-Inspired Design: An Overview Investigating Open Questions From the Broader Field of Design-by-Analogy\n.\nJournal of Mechanical Design\n136\n(\n111102\n).\nExternal Links:\nISSN 1050-0472\n,\nLink\n,\nDocument\nCited by:\n§1\n.\n[15]\nY. Gao, B. Su, L. Jiang, and F. Gao\n(2023-05)\nMulti-legged robots: progress and challenges\n.\nNational Science Review\n10\n(\n5\n),\npp. nwac214\n(\neng\n).\nExternal Links:\nISSN 2053-714X\n,\nDocument\nCited by:\n§1\n.\n[16]\nJ. Gu, Z. Ye, T. Rae-Grant, S. Wang, D. Zhao, J. Hester, V. A. Webster-Wood, and L. Yao\n(2025-09)\nOptimization and control of actuator networks in variable geometry truss systems using genetic algorithms\n.\nNature Communications\n16\n(\n1\n),\npp. 8432\n(\nen\n).\nExternal Links:\nISSN 2041-1723\n,\nLink\n,\nDocument\nCited by:\n§1\n,\n§4\n.\n[17]\nY. Guan, Z. Zhuang, Z. Zhang, and J. S. Dai\n(2023-05)\nDesign, Analysis, and Experiment of the Origami Robot Based on Spherical-Linkage Parallel Mechanism\n.\nJournal of Mechanical Design\n145\n(\n081701\n).\nExternal Links:\nISSN 1050-0472\n,\nLink\n,\nDocument\nCited by:\n§1\n.\n[18]\nD. Howard, A. E. Eiben, D. F. Kennedy, J. Mouret, P. Valencia, and D. Winkler\n(2019-01)\nEvolving embodied intelligence from materials to machines\n.\nNature Machine Intelligence\n1\n(\n1\n),\npp. 12–19\n(\nen\n).\nExternal Links:\nISSN 2522-5839\n,\nLink\n,\nDocument\nCited by:\n§1\n.\n[19]\nY. Hu, L. Anderson, T. Li, Q. Sun, N. Carr, J. Ragan-Kelley, and F. Durand\n(2020)\nDiffTaichi: differentiable programming for physical simulation\n.\narXiv preprint arXiv:1910.00935\n.\nCited by:\n§1\n,\n§2.2\n,\n§2.3.3\n,\n§3.1\n.\n[20]\nA. J. Ijspeert\n(2008)\nCentral pattern generators for locomotion control in animals and robots: a review\n.\nNeural networks\n21\n(\n4\n),\npp. 642–653\n.\nCited by:\n§2.1.2\n.\n[21]\nY. Jia, C. Wang, and X. S. Zhang\n(2024-08)\nFEniTop: a simple FEniCSx implementation for 2D and 3D topology optimization supporting parallel computing\n.\nStructural and Multidisciplinary Optimization\n67\n(\n8\n),\npp. 140\n(\nen\n).\nExternal Links:\nISSN 1615-1488\n,\nLink\n,\nDocument\nCited by:\n§1\n.\n[22]\nC. Jiang, C. Schroeder, J. Teran, A. Stomakhin, and A. Selle\n(2016)\nThe material point method for simulating continuum materials\n.\nIn\nACM SIGGRAPH 2016 Courses\n,\nSIGGRAPH ’16\n,\nNew York, NY, USA\n.\nExternal Links:\nISBN 9781450342896\n,\nLink\n,\nDocument\nCited by:\n§1\n.\n[23]\nA. C. Karacakol, Y. Alapan, S. O. Demir, and M. Sitti\n(2025-03)\nData-driven design of shape-programmable magnetic soft materials\n.\nNature Communications\n16\n(\n1\n),\npp. 2946\n(\nen\n).\nExternal Links:\nISSN 2041-1723\n,\nLink\n,\nDocument\nCited by:\n§1\n.\n[24]\nR. Kinjo, Y. Shimizu, Y. Morimoto, and S. Takeuchi\n(2024)\nBiohybrid bipedal robot powered by skeletal muscle tissue\n.\nMatter\n7\n(\n3\n),\npp. 1026–1041\n.\nCited by:\n§1\n,\n§4\n.\n[25]\nH. Kobayashi, F. Gholami, S. M. Montgomery, M. Tanaka, L. Yue, C. Yuhn, Y. Sato, A. Kawamoto, H. J. Qi, and T. Nomura\n(2024-07)\nComputational synthesis of locomotive soft robots by topology optimization\n.\nScience Advances\n10\n(\n30\n),\npp. eadn6129\n.\nExternal Links:\nLink\n,\nDocument\nCited by:\n§1\n,\n§1\n.\n[26]\nA. Kotikian, R. L. Truby, J. W. Boley, T. J. White, and J. A. Lewis\n(2018)\n3D Printing of Liquid Crystal Elastomeric Actuators with Spatially Programed Nematic Order\n.\nAdvanced Materials\n30\n(\n10\n),\npp. 1706164\n(\nen\n).\nExternal Links:\nISSN 1521-4095\n,\nLink\n,\nDocument\nCited by:\n§1\n.\n[27]\nS. Kriegman, D. Blackiston, M. Levin, and J. Bongard\n(2020-01)\nA scalable pipeline for designing reconfigurable organisms\n.\nProceedings of the National Academy of Sciences\n117\n(\n4\n),\npp. 1853–1859\n.\nExternal Links:\nLink\n,\nDocument\nCited by:\n§1\n.\n[28]\nP. Kumar, A. Saxena, and R. A. Sauer\n(2018-10)\nComputational Synthesis of Large Deformation Compliant Mechanisms Undergoing Self and Mutual Contact\n.\nJournal of Mechanical Design\n141\n(\n012302\n).\nExternal Links:\nISSN 1050-0472\n,\nLink\n,\nDocument\nCited by:\n§1\n.\n[29]\nR. H. Lee, E. A. Mulder, and J. B. Hopkins\n(2022)\nMechanical neural networks: architected materials that learn behaviors\n.\nScience Robotics\n7\n(\n71\n),\npp. eabq7278\n.\nCited by:\n§4\n.\n[30]\nM. Li, L. Kong, and S. Kriegman\n(2024)\nGenerating freeform endoskeletal robots\n.\narXiv preprint arXiv:2412.01036\n.\nCited by:\n§1\n,\n§1\n.\n[31]\nX. Liang, J. Tang, Y. Zhong, B. Gao, H. Qian, and H. Wu\n(2024)\nPhysical reservoir computing with emerging electronics\n.\nNature Electronics\n7\n(\n3\n),\npp. 193–206\n.\nCited by:\n§4\n.\n[32]\nT. S. Lumpe and K. Shea\n(2023-03)\nComputational Design of Multi-State Lattice Structures With Finite Mechanisms for Shape Morphing\n.\nJournal of Mechanical Design\n145\n(\n071701\n).\nExternal Links:\nISSN 1050-0472\n,\nLink\n,\nDocument\nCited by:\n§1\n.\n[33]\nP. Ma, T. Du, J. Z. Zhang, K. Wu, A. Spielberg, R. K. Katzschmann, and W. Matusik\n(2021-07)\nDiffAqua: a differentiable computational design pipeline for soft underwater swimmers with shape interpolation\n.\nACM Trans. Graph.\n40\n(\n4\n),\npp. 132:1–132:14\n.\nExternal Links:\nISSN 0730-0301\n,\nLink\n,\nDocument\nCited by:\n§1\n.\n[34]\nD. Matthews, A. Spielberg, D. Rus, S. Kriegman, and J. Bongard\n(2023-10)\nEfficient automatic design of robots\n.\nProceedings of the National Academy of Sciences\n120\n(\n41\n),\npp. e2305180120\n.\nExternal Links:\nLink\n,\nDocument\nCited by:\n§1\n,\n§1\n.\n[35]\nR. Newbury, J. Collins, K. He, J. Pan, I. Posner, D. Howard, and A. Cosgun\n(2024)\nA review of differentiable simulators\n.\nIEEE Access\n12\n(\n),\npp. 97581–97604\n.\nExternal Links:\nDocument\nCited by:\n§1\n.\n[36]\nA. Parsa, C. S. O’Hern, R. Kramer-Bottiglio, and J. Bongard\n(2024)\nGradient-based design of computational granular crystals\n.\narXiv preprint arXiv:2404.04825\n.\nCited by:\n§1\n.\n[37]\nF. L. Roth, R. L. Driscoll, and W. L. Holt\n(1943-03)\nFrictional Properties of Rubber\n.\nRubber Chemistry and Technology\n16\n(\n1\n),\npp. 155–177\n.\nExternal Links:\nISSN 1943-4804, 0035-9475\n,\nLink\n,\nDocument\nCited by:\n§3.3\n.\n[38]\nY. Sato, C. Yuhn, H. Kobayashi, A. Kawamoto, and T. Nomura\n(2025-09)\nComputational co-design of structure and feedback controller for locomoting soft robots\n.\nStructural and Multidisciplinary Optimization\n68\n(\n9\n),\npp. 185\n(\nen\n).\nExternal Links:\nISSN 1615-1488\n,\nLink\n,\nDocument\nCited by:\n§1\n.\n[39]\nC. Schaff, A. Sedal, and M. R. Walter\n(2022-06)\nSoft robots learn to crawl: jointly optimizing design and control with sim-to-real transfer\n.\nIn\nProceedings of Robotics: Science and Systems\n,\nCited by:\n§1\n.\n[40]\nA. Schulz, C. Sung, A. Spielberg, W. Zhao, R. Cheng, E. Grinspun, D. Rus, and W. Matusik\n(2017-09)\nInteractive robogami: An end-to-end system for design of robots with ground locomotion\n.\nThe International Journal of Robotics Research\n36\n(\n10\n),\npp. 1131–1147\n(\nEN\n).\nExternal Links:\nISSN 0278-3649\n,\nLink\n,\nDocument\nCited by:\n§1\n.\n[41]\nD. S. Shah, J. W. Booth, R. L. Baines, K. Wang, M. Vespignani, K. Bekris, and R. Kramer-Bottiglio\n(2022-08)\nTensegrity Robotics\n.\nSoft Robotics\n9\n(\n4\n),\npp. 639–656\n(\nEN\n).\nExternal Links:\nISSN 2169-5172\n,\nLink\n,\nDocument\nCited by:\n§1\n.\n[42]\nA. Spielberg, T. Du, Y. Hu, D. Rus, and W. Matusik\n(2023-01)\nAdvanced soft robot modeling in ChainQueen\n.\nRobotica\n41\n(\n1\n),\npp. 74–104\n(\nen\n).\nExternal Links:\nISSN 0263-5747, 1469-8668\n,\nLink\n,\nDocument\nCited by:\n§1\n.\n[43]\nA. Spielberg, A. Zhao, Y. Hu, T. Du, W. Matusik, and D. Rus\n(2019)\nLearning-In-The-Loop Optimization: End-To-End Control And Co-Design Of Soft Robots Through Learned Deep Latent Representations\n.\nIn\nAdvances in Neural Information Processing Systems\n,\nVol.\n32\n.\nExternal Links:\nLink\nCited by:\n§1\n.\n[44]\nA. Spinos and M. Yim\n(2022)\nA linking invariant for truss robot motion planning\n.\nIEEE Robotics and Automation Letters\n7\n(\n2\n),\npp. 1424–1430\n.\nExternal Links:\nDocument\nCited by:\n§1\n.\n[45]\nL. Strgar and S. Kriegman\n(2025)\nAccelerated co-design of robots through morphological pretraining\n.\narXiv preprint arXiv:2502.10862\n.\nCited by:\n§1\n,\n§4\n.\n[46]\nL. Strgar, D. Matthews, T. Hummer, and S. Kriegman\n(2024-07)\nEvolution and learning in differentiable robots\n.\nIn\nProceedings of Robotics: Science and Systems\n,\nDelft, Netherlands\n.\nExternal Links:\nDocument\nCited by:\n§1\n,\n§4\n.\n[47]\nL. Sun, Y. Yu, Z. Chen, F. Bian, F. Ye, L. Sun, and Y. Zhao\n(2020)\nBiohybrid robotics with living cell actuation\n.\nChemical Society Reviews\n49\n(\n12\n),\npp. 4043–4069\n.\nCited by:\n§4\n.\n[48]\nM. van Diepen and K. Shea\n(2022-06)\nCo-Design of the Morphology and Actuation of Soft Robots for Locomotion\n.\nJournal of Mechanical Design\n144\n(\n083305\n).\nExternal Links:\nISSN 1050-0472\n,\nLink\n,\nDocument\nCited by:\n§1\n.\n[49]\nL. Wang, A. L. Evenchik, J. M. Yang, R. L. Truby, and W. Chen\n(2025-09)\nAutonomous codesign and fabrication of multistimuli-responsive material systems\n.\nScience Advances\n11\n(\n37\n),\npp. eadx4409\n.\nExternal Links:\nLink\n,\nDocument\nCited by:\n§1\n.\n[50]\nL. Wang\n(2025-10)\nCo-design of magnetic soft robots with large deformation and contacts via material point method and topology optimization\n.\nComputer Methods in Applied Mechanics and Engineering\n445\n,\npp. 118205\n.\nExternal Links:\nISSN 0045-7825\n,\nLink\n,\nDocument\nCited by:\n§1\n.\n[51]\nT. J. Wang, J. Zheng, P. Ma, Y. Du, B. Kim, A. Spielberg, J. Tenenbaum, C. Gan, and D. Rus\n(2023-12)\nDiffuseBot: Breeding Soft Robots With Physics-Augmented Generative Diffusion Models\n.\nAdvances in Neural Information Processing Systems\n36\n,\npp. 44398–44423\n(\nen\n).\nExternal Links:\nLink\nCited by:\n§1\n.\n[52]\nT. Wang, P. Ma, A. E. Spielberg, Z. Xian, H. Zhang, J. B. Tenenbaum, D. Rus, and C. Gan\n(2023)\nSoftZoo: a soft robot co-design benchmark for locomotion in diverse environments\n.\narXiv preprint arXiv:2303.09555\n.\nCited by:\n§1\n.\n[53]\nV. A. Webster-Wood, M. Guix, N. W. Xu, B. Behkam, H. Sato, D. Sarkar, S. Sanchez, M. Shimizu, and K. K. Parker\n(2022-11)\nBiohybrid robots: recent progress, challenges, and perspectives\n.\nBioinspiration & Biomimetics\n18\n(\n1\n),\npp. 015001\n(\nen\n).\nExternal Links:\nISSN 1748-3190\n,\nLink\n,\nDocument\nCited by:\n§1\n.\n[54]\nT. Xue, S. Liao, Z. Gan, C. Park, X. Xie, W. K. Liu, and J. Cao\n(2023-10)\nJAX-FEM: A differentiable GPU-accelerated 3D finite element solver for automatic inverse design and mechanistic data science\n.\nComputer Physics Communications\n291\n,\npp. 108802\n.\nExternal Links:\nISSN 0010-4655\n,\nLink\n,\nDocument\nCited by:\n§1\n.\n[55]\nC. Yuhn, Y. Sato, H. Kobayashi, A. Kawamoto, and T. Nomura\n(2023)\n4D topology optimization: integrated optimization of the structure and self-actuation of soft bodies for dynamic motions\n.\nComputer Methods in Applied Mechanics and Engineering\n414\n,\npp. 116187\n.\nExternal Links:\nISSN 0045-7825\n,\nDocument\n,\nLink\nCited by:\n§1\n,\n§2.3.1\n,\n§2.3.2\n.\n[56]\nB. Zhang, J. Shen, Z. He, Q. Wu, J. Xiong, and Z. Xia\n(2025)\nMorphological design methodologies of soft robots\n.\nThe Innovation Informatics\n1\n(\n1\n),\npp. 100012\n.\nExternal Links:\nISSN 3105-8515\n,\nDocument\n,\nLink\nCited by:\n§1\n.\n[57]\nC. Zhang, X. Yin, R. Chen, K. Ju, Y. Hao, T. Wu, J. Sun, H. Yang, and Y. Xu\n(2024)\nA review on reprogrammable bistable structures\n.\nSmart materials and structures\n33\n(\n9\n),\npp. 093001\n.\nCited by:\n§1\n.\n[58]\nZ. Zhao and X. S. Zhang\n(2022-01)\nTopology optimization of hard-magnetic soft materials\n.\nJournal of the Mechanics and Physics of Solids\n158\n,\npp. 104628\n.\nExternal Links:\nISSN 0022-5096\n,\nLink\n,\nDocument\nCited by:\n§1\n.",
    "preview_text": "Replicating and surpassing the autonomy of natural organisms remains a long-standing goal in robotics. Yet most robotic systems have their structure, materials, and control designed separately, in sharp contrast to the co-evolution in nature. This separation often leads to suboptimal designs, and we still have a limited understanding of the individual and collective contributions of these design entities. In this work, we propose a gradient-based co-design framework that simultaneously optimizes the topology, material distribution, and control policy of a truss-lattice robot. The framework embeds mixed-type topological and material variables into a continuous design space and integrates a neural network controller within a differentiable simulator, capturing their interactions and enabling efficient gradient calculation via automatic differentiation. Furthermore, we develop a constrained optimization to navigate the highly non-convex design landscape and jointly optimize all design entities. Case studies demonstrate that the proposed framework consistently discovers diverse locomotion strategies that outperform baselines obtained through separated design. The framework is also flexible to accommodate different functional requirements and boundary conditions. Using this framework, we further extract design insights that reveal the individual and collective effects of different entities on robotic performance. The proposed framework provides a computational foundation for the autonomous co-design of robotic systems, capable of reconfiguration, locomotion, and other complex autonomous behaviors.\n\nCOSMIC: Concurrent Optimization of Structure, Material, and Integrated Control for robotic systems\nQinsong Guo\nDept. of Mechanical Engineering\nCarnegie Mellon University\nPittsburgh, PA 15213\ntimg@andrew.cmu.edu\n&\nLiwei Wang\nDept. of Mechanical Engineering\nCarnegie Mellon University\nPittsburgh, PA 15213\nliweiw@andrew.cmu.edu\nCorresponding author\nAbstract\nReplicating and surpass",
    "is_relevant": false,
    "relevance_score": 0.0,
    "extracted_keywords": [],
    "one_line_summary": "该论文主要关注机器人结构、材料和控制的联合优化，与强化学习、VLA、VLM等关键词无关。",
    "detailed_summary": "",
    "qa_pairs": [],
    "is_hidden": false,
    "is_starred": false,
    "flag": true,
    "published_date": "2026-05-12T19:00:01Z",
    "created_at": "2026-05-26T15:55:59.382105",
    "updated_at": "2026-05-26T15:55:59.382113"
}